Workbook

Sheet Dashboard
A1: BSU REMIS - Research Publications Monitoring Dashboard
A2: Last Updated: | B2: 2026-01-27 14:05:06
A4: KEY PERFORMANCE INDICATORS
A5: Total Publications (All Years) | E5: Publications 2025
A6: =Publications_Summary!B2 -> 401 | E6: =Publications_Summary!B3 -> 54
A8: Total Faculty Tracked | E8: Avg H-Index
A9: =Faculty_Metrics!B2 -> 59 | E9: =Faculty_Metrics!B3 -> 3.3389831
A12: ALERTS & NOTIFICATIONS
A13: Alert Type | B13: Description | C13: Count | D13: Status
A14: Missing H-Index | B14: Faculty without H-index data | C14: =Faculty_Metrics!B4 -> 40 | D14: Review
A15: Low Citations | B15: Faculty with <100 citations | C15: =Faculty_Metrics!B5 -> 3 | D15: Monitor
A16: No Recent Pubs | B16: Faculty with no 2024-2025 pubs | C16: =Faculty_Metrics!B6 -> 56 | D16: Action Needed
A18: PUBLICATION TRENDS BY YEAR
A19: Year | B19: Publications
A20: 2025 | B20: =Publications_Summary!B4 -> 0
A21: 2024 | B21: =Publications_Summary!B5 -> 54
A22: 2023 | B22: =Publications_Summary!B6 -> 61
A23: 2022 | B23: =Publications_Summary!B7 -> 53
A24: 2021 | B24: =Publications_Summary!B8 -> 57
A25: 2020 | B25: =Publications_Summary!B9 -> 44
A26: 2018-2019 | B26: =Publications_Summary!B10 -> 48
A27: 2017-below | B27: =Publications_Summary!B11 -> 84

Sheet Publications_Summary
A1: PUBLICATION STATISTICS SUMMARY
A2: Total Publications (All Years) | B2: =SUM(B4:B11) -> 401
A3: Publications 2025 | B3: =COUNTA(Data_2025!D:D)-1 -> 54
A5: 2025 | B5: =COUNTA(Data_2025!D:D)-1 -> 54
A6: 2024 | B6: =COUNTA(Data_2024!D:D)-1 -> 61
A7: 2023 | B7: =COUNTA(Data_2023!D:D)-1 -> 53
A8: 2022 | B8: =COUNTA(Data_2022!D:D)-1 -> 57
A9: 2021 | B9: =COUNTA(Data_2021!D:D)-1 -> 44
A10: 2020 | B10: =COUNTA(Data_2020!D:D)-1 -> 48
A11: 2018-2019 | B11: =COUNTA(Data_2018_2019!D:D)-1 -> 84
A12: 2017 & Below | B12: =COUNTA(Data_2017_below!D:D)-1 -> 380

Sheet Faculty_Metrics
A1: FACULTY RESEARCH METRICS
A2: Total Faculty/Researchers | B2: =COUNTA(Faculty_Data!A:A)-1 -> 59
A3: Average H-Index | B3: =AVERAGEIF(Faculty_Data!C:C,">0") -> 3.3389831
A4: Missing H-Index Count | B4: =COUNTBLANK(Faculty_Data!C2:C100) -> 40
A5: Faculty with <100 Citations | B5: =COUNTIFS(Faculty_Data!B:B,"<100",Faculty_Data!B:B,">0") -> 3
A6: Faculty without Recent Pubs | B6: =B2-SUMPRODUCT((COUNTIF(Data_2024!E:E,Faculty_Data!A2:A100)>0)+(COUNTIF(Data_2025!E:E,Faculty_Data!A2:A100)>0)) -> 56

Sheet Tracking_Log
A1: PUBLICATION TRACKING LOG
A2: Date | B2: Action Type | C2: Year | D2: Publication Title | E2: Author(s) | F2: College/Institute | G2: Publication Type | H2: Status | I2: Updated By | J2: Notes
A3: 2026-01-27 | B3: Initial Setup | C3: System | D3: Monitoring system created | E3: System Admin

Sheet Faculty_Data
A1: Name | B1: Citations | C1: H-Index | D1: i-10 Index | E1: Scholar Account
A2: Roscinto Ian C. Lumbres | B2: 340 | C2: 11 | D2: 14 | E2: https://scholar.google.com/citations?user=DMax5CIAAAAJ&hl=en&oi=ao
A3: Cheryll C. Launio | B3: 588 | C3: 13 | D3: 15 | E3: https://scholar.google.com/citations?hl=en&user=Lqml6uwAAAAJ
A4: Jones Napaldet | B4: 192 | C4: 8 | D4: 7 | E4: https://scholar.google.com/citations?hl=en&user=4oMSPvIAAAAJ
A5: Sherlyn Tipayno | B5: 472 | C5: 8 | D5: 8 | E5: Sherlyn Tipayno - Google Scholar
A6: Nordalyn Pedroche | B6: 87 | C6: 5 | D6: 4 | E6: https://scholar.google.com/citations?hl=en&user=FzNIYCUAAAAJ
A7: Cynthia Garambas | C7: 2 | D7: 0 | E7: https://scholar.google.com/citations?hl=en&user=Ih7poOcAAAAJ
A8: Ruth S. Batani | C8: 3 | D8: 2 | E8: https://scholar.google.com/citations?hl=en&user=YN-qtvgAAAAJ
A9: Joyce N. Paing | C9: 3 | D9: 2 | E9: https://scholar.google.com/citations?hl=en&user=ow8JcAYAAAAJ
A10: Kenneth A. Laruan | C10: 3 | D10: 2 | E10: https://scholar.google.com/citations?hl=en&user=PyO6wrQAAAAJ
A11: Janet P. Pablo | C11: 2 | D11: 0 | E11: https://scholar.google.com/citations?hl=en&user=yAkouz0AAAAJ
A12: Jude Tayaben | B12: 554 | C12: 11 | D12: 13 | E12: https://scholar.google.com/citations?hl=en&user=P9R_wQsAAAAJ
A13: Nova D. Doyog | B13: 159 | C13: 8 | D13: 7 | E13: https://scholar.google.com/citations?hl=en&user=-WSRHRgAAAAJ
A14: Bernard Peter O. Daipan | C14: 4 | D14: 2 | E14: https://scholar.google.com/citations?hl=en&user=Wh-UtCMAAAAJ
A15: Grace S. Backian | C15: 2 | D15: 1 | E15: https://scholar.google.com/citations?hl=en&user=PA45re8AAAAJ
A16: Dalen T. Meldoz | C16: 2 | D16: 1 | E16: https://scholar.google.com/citations?hl=en&user=PA45re8AAAAJ
A17: Esther Botangen | C17: 3 | D17: 1 | E17: https://scholar.google.com/citations?hl=en&user=JVLR2AoAAAAJ
A18: Lawrence C. Caranto | B18: 535 | C18: 7 | D18: 6 | E18: https://scholar.google.com/citations?hl=en&user=mb1fOpoAAAAJ
A19: Ann Heather B. Kiwang | C19: 1 | D19: 0 | E19: https://scholar.google.com/citations?hl=en&user=hP8VWfsAAAAJ
A20: Daniel Jr. Balbin | C20: 2 | D20: 0 | E20: https://scholar.google.com/citations?hl=en&user=YXd9peYAAAAJ
A21: Marissa Parao | C21: 3 | D21: 1 | E21: https://scholar.google.com/citations?hl=en&user=KiiQ4foAAAAJ
A22: Darwin Basquial | C22: 1 | D22: 0 | E22: https://scholar.google.com/citations?hl=en&user=Vv8YJoEAAAAJ
A23: Esther Josephine D. Sagalla | C23: 2 | D23: 1 | E23: https://scholar.google.com/citations?hl=en&user=poGlUkEAAAAJ
A24: Bretel Dolipas | B24: 395 | C24: 6 | D24: 1 | E24: https://scholar.google.com/citations?hl=en&user=DREmjywAAAAJ
A25: Ronda B. Tullay | C25: 1 | D25: 0 | E25: https://scholar.google.com/citations?hl=en&user=pKmp2BYAAAAJ
A26: Marvin Valentin | B26: 211 | C26: 7 | D26: 7 | E26: https://scholar.google.com/citations?hl=en&user=8_fUSUcAAAAJ
A27: Renebeth Gatudan Donguiz | C27: 1 | D27: 0 | E27: https://scholar.google.com/citations?hl=en&user=y-L2ZTIAAAAJ
A28: John Rey Pelila | C28: 4 | D28: 1 | E28: https://scholar.google.com/citations?hl=en&user=vc_NS64AAAAJ
A29: Jhordan T. Cuilan | B29: 89 | C29: 6 | D29: 5 | E29: https://scholar.google.com/citations?hl=en&user=Y5Ot_3wAAAAJ
A30: Gleemoore C. Makie | C30: 2 | D30: 1 | E30: https://scholar.google.com/citations?hl=en&user=7OaxIsYAAAAJ
A31: Jesson Del-amen | C31: 2 | D31: 0 | E31: https://scholar.google.com/citations?hl=en&user=xuGuANoAAAAJ
A32: Teresita D. Masangcay | C32: 1 | D32: 0 | E32: https://scholar.google.com/citations?hl=en&user=MsVyn6QAAAAJ
A33: Conrado C. Bao-idang | C33: 2 | D33: 0 | E33: https://scholar.google.com/citations?hl=en&user=ekZGp3EAAAAJ
A34: Nora Hill Evasco | C34: 1 | D34: 0 | E34: https://scholar.google.com/citations?hl=en&user=I4qXom8AAAAJ
A35: Stanley F. Angonos, Jr. | C35: 1 | D35: 0 | E35: https://scholar.google.com/citations?hl=en&user=lH542fYAAAAJ
A36: Joseph B. Quinto | C36: 4 | D36: 2 | E36: https://scholar.google.com/citations?hl=en&user=hTEK3WYAAAAJ
A37: Elizabeth A. Lascano | C37: 3 | D37: 0 | E37: https://scholar.google.com/citations?hl=en&user=W67OyrcAAAAJ
A38: Divina Yango | C38: 1 | D38: 1 | E38: https://scholar.google.com/citations?hl=en&user=ep9pn1kAAAAJ
A39: Lesley Dale Umayat | C39: 1 | D39: 0 | E39: https://scholar.google.com/citations?hl=en&user=-FTcY0gAAAAJ
A40: Noel Waclet Cabfilan | C40: 3 | D40: 0 | E40: https://scholar.google.com/citations?hl=en&user=eRYjj_cAAAAJ
A41: Apler J. Bansiong | B41: 77 | C41: 5 | D41: 2 | E41: https://scholar.google.com/citations?hl=en&user=Y3vamKYAAAAJ
A42: Dolores E. Alawas | C42: 2 | D42: 0 | E42: https://scholar.google.com/citations?hl=en&user=URnAL6wAAAAJ
A43: Janet Lynn Balagtey | C43: 1 | D43: 1 | E43: https://scholar.google.com/citations?hl=en&user=IzJUUEkAAAAJ
A44: Von Y. Amado | C44: 2 | D44: 0 | E44: https://scholar.google.com/citations?hl=en&user=tvxpjX0AAAAJ
A45: Frevy Teofilo Orencia | C45: 3 | D45: 1 | E45: https://scholar.google.com/citations?hl=en&user=x8PlsbMAAAAJ
A46: Maricel Guron | C46: 4 | D46: 2 | E46: https://scholar.google.com/citations?hl=en&user=SCSvSk0AAAAJ
A47: Imelda Parcasio | C47: 3 | D47: 0 | E47: https://scholar.google.com/citations?hl=en&user=-zoRhjwAAAAJ
A48: Russell B. Dolendo | C48: 2 | D48: 1 | E48: https://scholar.google.com/citations?hl=en&user=a8uUB_UAAAAJ
A49: Matyline Camfili | C49: 1 | D49: 0 | E49: https://scholar.google.com/citations?hl=en&user=RPjtg8cAAAAJ
A50: Kristine Baniqued-Dela Cruz | C50: 1 | D50: 1 | E50: https://scholar.google.com/citations?hl=en&user=A9oN0v8AAAAJ
A51: Jennifer Paltiyan- Bugtong | C51: 2 | D51: 0 | E51: https://scholar.google.com/citations?hl=en&user=-lBMSQwAAAAJ
A52: Chester B. Esnara | C52: 3 | D52: 0 | E52: https://scholar.google.com/citations?hl=en&user=QgG25c0AAAAJ
A53: Lynn J. Talkasen | C53: 1 | D53: 0 | E53: https://scholar.google.com/citations?hl=en&user=7KEntRAAAAAJ
... A60: Jennifer Lynn S. Ramos | C60: 4 | D60: 1 | E60: https://scholar.google.com/citations?user=CoQhGC4AAAAJ&hl=tl&oi=ao

Sheet Data_2025
A1: No. | B1: Year | C1: College/Institute | D1: Title | E1: Author(s) | F1: Pub Type | G1: Journal/Book | H1: Category | I1: Keywords | J1: URL | K1: Citations | L1: Remarks
A2: 1 | B2: Jan to June 2025 | C2: CPAG/OSS | D2: Meanings and Experiences of Survival Among Filipino Women Survivors of Abuse | E2: Carolyn Busongan Gano and Angeli Tuzon Austria | F2: Journal | G2: Pertanika Journal Social Sciences and Humanities | H2: Peer-reviewed | I2: Coping strategies, Filipino women, the journey of survival, the meaning of survival, women empowerment, women survivors of abuse | J2: https://doi.org/10.47836/pjssh.33.1.03
A3: 2 | B3: Jan to June 2025 | C3: CA | D3: On-Farm Evaluation of Auxin-Treated Sugarcane Bud Chip for Enhanced Growth and Yield | E3: Darwin M Cacal, Janet P Pablo, Darwin A Basquial, Esther Josephine D Sagalla and Leila Mary A Ayban | F3: Journal | G3: Journal of Agriculture and Forest Meteorology Studies | H3: Peer-reviewed | I3: Sugarcane, Budchip, Auxin, Internodes, Bagasse yield | J3: https://manuscriptscientific.com/images/cafe8f883907979ef4cb2f2d57ea9890.pdf | L3: Co-authors
A4: 3 | B4: Jan to June 2025 | C4: CNS | D4: Water quality of Balili River before, during and after COVID: lessons learned and ways forwards for tropical river remediation | E4: Fernie D. SitSit, Romeo M. Dizon & Jones T. Napaldet | F4: Journal | G4: Aquatic Ecology | H4: Scopus/Web of Science | I4: Self-purification, COVID, Water quality, Water quality index, Balili River | J4: https://doi.org/10.1007/s10452-024-10151-0
A5: 4 | B5: Jan to June 2025 | C5: CNAS | D5: Engineering Students’ Expectations about Calculus-based Physics | E5: Thrysha B. Dolipas & Bretel B. Dolipas | F5: Journal | G5: International Journal of Multidisciplinary Educational Research and Innovation 3 (1):284-297 | H5: peer-reviewed | I5: Physics expectations, calculus- based, Physics, sex, senior high school, strand completed | J5: https://philpapers.org/rec/DOLESE
A6: 5 | B6: Jan to June 2025 | C6: CAH | D6: Assessment of Kankanaey Language Resources: A Document Review | E6: Ronda Bataclao Tullay, John Rey Osben Pelila | F6: Journal | G6: Pakistan Journal of Life and Social Sciences | H6: Scopus | I6: Language Assessment, Multilingual Education, Philippines | J6: https://doi.org/10.57239/PJLSS-2025-23.1.00497
A7: 6 | B7: Jan to June 2025 | C7: CNAS | D7: Graduate’s Personal and Professional Impact Assessment: A Degree Program Sustainability Criteria | E7: Bretel B. Dolipas | Maria Azucena B. Lubrica | Serano L. Oryan | Freda Kate D. Samuel | Precious M. Valentin | Joel V. Lubrica | Julie A. Buasen | Phil S. Ocampo | F7: Journal | G7: Journal of Interdisciplinary Perspectives | H7: Peer-reviewed but monthly released with 65 articles per volume | J7: https://www.ejournals.ph/article.php?id=26115
A8: 7 | B8: Jan to June 2025 | C8: CAH | D8: How is English as a Lingua Franca (ELF) Transforming Education in ASEAN Universities? | E8: Mary Faye Suoc, Joanna Lastino, Judilyne Lukingan, Mark Rendel Baraoil, John Rey Pelila | F8: Journal | G8: Journal of Multidisciplinary Research and Development, 2(1), 102–115. | H8: peer-reviewed | I8: stematic literature review, English proficiency, higher education institutions, lingua franca, ASEAN | J8: https://doi.org/10.56916/jmrd.v2i1.1024
A9: 8 | B9: Jan to June 2025 | C9: CPAG | D9: Empirical evidence on the practice of latitude of discretion in personnel selection: Basis for an informed intervention | E9: Renebeth G. Donguiz1*, Narda A. Garcia | F9: Journal | G9: HO CHI MINH CITY OPEN UNIVERSITY JOURNAL OF SCIENCE | H9: peer-reviewed | I9: civil service; governance; human resource; latitude of discretion; merit selection | J9: https://journalofscience.ou.edu.vn/index.php/soci-en/article/view/3553/2329
A10: 9 | B10: Jan to June 2025 | C10: CA | D10: Productivity of corn (Zea mays) under varying drought duration and nitrogen application at La, Trinidad, Benguet | E10: J.P. Pablo G.M. Awidan D.M. Cacal | F10: Journal | G10: Asian Journal of Agriculture and Rural Development Volume 15, Issue 1 (2025): 30-38 | H10: Scopus | I10: Corn, Drought, Nitrogen, Productivity, Vegetative, Water stress, Zea mays | J10: https://archive.aessweb.com/index.php/5005/article/view/5299/8167
A11: 10 | B11: Jan to June 2025 | C11: CPAG | D11: Home-Based Community Internship Model: Exploring Employment Outcomes and Educational Strategies in Public Administration in Benguet, Philippines | E11: Atty. Julie M. Binaldo-Velasco | F11: Journal | G11: Pedagogy Review: An International Journal of Educational Theories, Approaches and Strategies 2025, Vol. 4, No.2, 214 – 228 | | H11: peer-reviewed | I11: home-based internship, employment outcomes, educational strategies, public administration | J11: https://doi.org/10.62718/vmca.pr-ijetas.4.2.SC-0225-021
A12: 11 | B12: Jan to June 2025 | C12: CAH | D12: Assessing archaism in Philippine Indigenous languages: the case of Kankanaey as spoken in Mankayan, Benguet, Philippines | E12: John Rey Osben Pelila, Shirley Lacson Ayao-ao | F12: Journal | G12: AlterNative: An International Journal of Indigenous Peoples Volume 21, Issue 1 Pages: 54 - 63 | H12: Web of Science | I12: archaism Indigenous people language assessment mixed-method design Philippines | J12: https://doi.org/10.1177/11771801241309727
A13: 12 | B13: Jan to June 2025 | C13: CAH | D13: How Do Schools and Community Influence Indigenous Youth's Perceptions of English? | E13: Liaa Eve Dalilis Tacio, John Rey Osben Pelila | F13: Journal | G13: Indonesian Journal of Research and Educational Review Volume 4, No. 2, 2025, pp 263 - 274 | H13: peer-reviewed | I13: English as a dominant language, Indigenous youth, Language, Phenomenological research, Philippines | J13: https://doi.org/10.51574/ijrer.v4i2.2851
A14: 13 | B14: Jan to June 2025 | C14: CE | D14: Development of a multi-commodity hammer mill for smallscale milling operation | E14: E N Dominguez*, C P Basquial | F14: Journal | G14: IOP Conf. Series: Earth and Environmental Science 1477 (2025) 012051 | H14: Scopus | J14: 10.1088/1755-1315/1477/1/012051
A15: 14 | B15: Jan to June 2025 | C15: CAH | D15: Semantics of Cardinal Directions in Benguet Cultural Practices | E15: John Rey Pelila, Von Ameri Escobar, Jessa Mariel Pilorin, Geraldine Wakat | F15: Journal | G15: Scholar: Human Sciences, 17(1), 317-327. | H15: peer-reviewed | I15: Linguistics, Culture, Meaning, Language Education, Philippines | J15: https://doi.org/10.14456/shserj.2025.30
A16: 15 | B16: Jan to June 2025 | C16: CHK | D16: Bridging gaps, wearable tech, apps and physical activity in older adults | E16: Charvet Caytap | F16: Journal | G16: Scientific Journal of Sport and Performance, 4(4), 470–479. | H16: peer-reviewed | I16: PrEAP model, Wearable trackers, Smart phone apps, Technology adoption, Healthcare, Aging | J16: https://doi.org/10.55860/WXFV1725
A17: 16 | B17: Jan to June 2025 | C17: CNS | D17: Assessment of conservation benefits of ecotourism in secondary forest ecosystems using PD-ZTCM-WTP in Mt Yangbew, Benguet, Philippines | E17: Allen Rey S. POTINGAN, Collen C. COIS, Remo M. BASILIO, Jones T. NAPALDET | F17: Journal | G17: Taiwania 70(1): 156‒170 | H17: Scopus/Web of Science | I17: plant diversity, quantification of ecotourism benefits, Benguet, Zone Travel Cost Method, willingness to pay | J17: https://www.researchgate.net/profile/Jones-Napaldet/publication/389008974_Assessment_of_conservation_benefits_of_ecotourism_in_secondary_forest_ecosystems_using_PD-ZTCM-WTP_in_Mt_Yangbew_Benguet_Philippines/links/67b00585461fb56424db8398/Assessment-of-conservation-benefits-of-ecotourism-in-secondary-forest-ecosystems-using-PD-ZTCM-WTP-in-Mt-Yangbew-Benguet-Philippines.pdf
A18: 17 | B18: Jan to June 2025 | C18: BSU-Buguias | D18: The Influence of Online Learning on the Academic and Social Behaviors of College Students | E18: Gleemoore C. Makie, Mary Ruth V. Datario, Jocelda Nova C. Vidal | F18: Journal | G18: Journal of Interdisciplinary Perspectives | H18: Peer-reviewed but monthly released with 65 articles per volume | I18: Online learning; College students; Academic behavior, Social behavior | J18: https://www.researchgate.net/profile/Gleemoore-Makie/publication/390920397_The_influence_of_online_learning_on_the_academic_and_social_behaviors_of_college_students/links/68025810d1054b0207d5152f/The-Influence-of-Online-Learning-on-the-Academic-and-Social-Behaviors-of-College-Students.pdf
A19: 18 | B19: Jan to June 2025 | C19: CA | D19: Advancements in Chemiresistive and Electrochemical Sensing Materials for Detecting Volatile Organic Compounds in Potato and Tomato Plants | E19: Baba, T.; Janairo, L.G.; Maging, Novelyn.; Tañedo, H.S.; Concepcion, R., II; Magdaong, J.J.; Bantang, J.P.; Del-amen, J.; Culaba, A. | F19: Journal | G19: AgriEngineering 2025, 7, 166. | H19: Scopus/Web of Science | I19: polymer sensor; hybrid material; precision agriculture; sustainable agriculture; volatile organic compounds; wearable sensor | J19: https://doi.org/10.3390/agriengineering7060166
A20: 19 | B20: Jan to June 2025 | C20: CHK | D20: Rapid weight loss in combative sports | E20: Karn Jariya M. Amado | F20: Journal | G20: Scientific Journal of Sport and Performance, 4(3), 466–469. | H20: peer-reviewed | I20: RWL, Athletes, Sport medicine, Psychological effect, Physical activity psychology | J20: https://doi.org/10.55860/CTMQ9059
A21: 20 | B21: Jan to June 2025 | C21: CA | D21: Phenotypic Characterization and Correlation Analysis in Quinoa (Chenopodium quinoa Willd.) Entries Cultivated in Itogon and La Trinidad, Benguet | E21: Flori Joyce D. Cariño and Esther Josephine D. Sagalla | F21: Journal | G21: Mountain Journal of Science and Interdisciplinary Research vol. 85 no.1 | H21: Scopus | I21: Chenopodium quinoa, correlation Analysis, phenotypic characterization | J21: http://portal.bsu.edu.ph:8083/index.php/BRJ/article/view/459
A22: 14 | B22: Jan to June 2025
A23: 15 | B23: Jan to June 2025
A24: 16
A25: 17
A26: 18
A27: 19
A28: 20
A29: 21
A30: 22
A31: 23
A32: 24
A33: 25
A34: 26
A35: 27
... A61: 53
A62: 21 | B62: Jan to June 2025 | C62: CNAS | D62: Geographical Variation, Path Diagram, and Regression Tree of the Incidence and Severity of Potato Late Blight (Phytophthora infestans): The Obesrved Pattern in the Major Growing Areas in Benguet Province | E62: Han B. Bonoy and Precious M. Valentin | F62: Journal | G62: Mountain Journal of Science and Interdisciplinary Research vol. 85 no.1 | H62: Scopus | I62: Cluster analysis, path analysis, Cart model, disease tetrahedron, potato late blight | J62: http://portal.bsu.edu.ph:8083/index.php/BRJ/article/view/458
A63: 22 | B63: Jan to June 2025 | C63: NPRCRTC | D63: Impacts of Technology Interventions on Managing Fusarium Wilt in Sweetpotato in Bauko, Mountain Province | E63: Dalen T. Meldoz, Teresita S. Masangcay, Cynthia G. Kiswa, and Analiza V. Alzarate | F63: Journal | G63: Mountain Journal of Science and Interdisciplinary Research vol. 85 no.1 | H63: Scopus | I63: sweetpotato, tissue culture-derived plant, material, fusarium wilt | J63: http://portal.bsu.edu.ph:8083/index.php/BRJ/article/view/462
A64: 23 | B64: Jan to June 2025 | C64: HORTI/CA | D64: Fresh Pod Yield and Stability of NSIC-Approved Varieties of Pole Snap Bean (Phaseolus vulgaris (L.)) in Benguet | E64: Margie E. Bad-ey, Leoncia L. Tandang, Hector C. Gayomba, and Johnson G. Bagtila | F64: Journal | G64: Mountain Journal of Science and Interdisciplinary Research vol. 85 no.1 | H64: Scopus | I64: Pole Sap Bean, On-Farm Trial, Fresh Pod Yield, GxE Interaction, Stability | J64: https://doi.org/10.70884/mjsir.v85i1.456
A65: 24 | B65: Jan to June 2025 | C65: CVM | D65: Hygiene Knowledge,Attitudes, and Practices (KAP) of Retailers and their Association to E.coli Contamination in pork Sold in La Trinidad, Benguet | E65: Edlyn Mae N. Ciano | F65: Journal | G65: Mountain Journal of Science and Interdisciplinary Research vol. 85 no.1 | H65: Scopus | I65: KAP (Knowledge, Attitudes, and Practices), E. coli contamination, pork | J65: http://portal.bsu.edu.ph:8083/index.php/BRJ/article/view/457
A66: 25 | B66: Jan to June 2025 | C66: CIS | D66: Influences and Perceived Changes Caused by the Agricultural Radio Program to the Farmer Listeners in Benguet, Philippines | E66: Nora C. Sagayo | F66: Journal | G66: Mountain Journal of Science and Interdisciplinary Research vol. 85 no.1 | H66: Scopus | I66: Agri-Pinoy Cordillera, Agricultural radio program, rural community, Benguet, Cordillera | J66: http://portal.bsu.edu.ph:8083/index.php/BRJ/article/view/460
A67: 26 | B67: Jan to June 2025 | C67: CF | D67: Agroforestry within a Limestone Forest in Tuba, Benguet, the Philippines, Conserved and Managed through Public-Private Partnership Reveals High Species Richness and Diversity | E67: Bernard Peter O. Daipanand Conrado C. Bao-idang | F67: Journal | G67: Philippine Journal of science | H67: Clarivate (Web of Science - Zoological Records); Scopus from 2009 to present | I67: agroforestry, diversity, endemism, forest over limestone, public-private partnership, species richness | J67: https://philjournalsci.dost.gov.ph/wp-content/uploads/2025/07/agroforestry-within-a-limestone-forest-in-Tuba-Benguet_.pdf
A68: 27 | B68: Jan to June 2025 | C68: CTE | D68: Factors Contributing to The Stress of The Science PreService Teachers at A State University in Northern, Philippines During The Neo- Normal | E68: CECILIA B. SAMONTE | F68: Journal | G68: INTERNATIONAL JOURNAL OF ADVANCED MULTIDISCIPLINARY STUDIES | H68: open access peer reviewed | I68: Science pre-service teachers, factors contributing to stress, pre-service teaching, neo- normal, pandemic | J68: https://www.ijams-bbp.net/wp-content/uploads/2025/07/6-IJAMS-JUNE-2025-334-348.pdf
A69: 28 | B69: Jan to June 2025 | C69: CA | D69: Working Capital Management of Cooperatives in Selected Municipalities in Benguet | E69: Joe S. Pelchona, David Joseph L. Bognadon | F69: Journal | G69: International Journal for Multidisciplinary Research | H69: Peer-reviewed | I69: Working Capital, Multipurpose Cooperatives, Financial Position, Financial Performance | J69: https://www.researchgate.net/profile/Joe-Pelchona/publication/390228642_Working_Capital_Management_of_Cooperatives_in_Selected_Municipalities_in_Benguet/links/68734b48dd6b84447df831c4/Working-Capital-Management-of-Cooperatives-in-Selected-Municipalities-in-Benguet.pdf
A70: 29 | B70: Jan to June 2025 | C70: CAH | D70: WHY DO CAFES NEED TO B.I.T.E. THEIR NAMES AND NOT FORGET TO S.I.P.? | E70: Ezra Isaiah Kayat Balawag, John Rey Osben Pelila | F70: Journal | G70: E-Journal of English Language & Literature | H70: Peer-reviewed | I70: Case Study, Toponomastics, English-Named Cafes, Philippines | J70: https://www.researchgate.net/profile/John-Rey-Pelila/publication/390761716_Why_Do_Cafes_Need_to_BITE_Their_Names_and_Not_Forget_to_SIP/links/67fd320e60241d51400c25e8/Why-Do-Cafes-Need-to-BITE-Their-Names-and-Not-Forget-to-SIP.pdf
A71: 30 | B71: Jan to June 2025 | C71: CAH | D71: Kankanaey over +me: A dyadic comparison of 1996 and 2023 transla+ons | E71: John Rey Osben Pelila | F71: Journal | G71: JOURNAL OF LANGUAGE AND CULTURE | H71: Peer-reviewed | I71: linguistic variations, diachronic change, lexical comparison, Kankanaey language, Philippines | J71: https://www.researchgate.net/profile/John-Rey-Pelila/publication/393288714_Kankanaey_over_time_A_dyadic_comparison_of_1966_and_2023_translations/links/6865348f39c3583512061757/Kankanaey-over-time-A-dyadic-comparison-of-1966-and-2023-translations.pdf
A72: 31 | B72: Jan to June 2025 | C72: CAH | D72: Teaching and Learning English Grammar:Opportunities and Challenges in ASEAN Countries | E72: Merigilda C. Cando, John Rey O. Pelila, Keivy Xyrelle G. Manogan, Ivy Joy L. Anagara, Angel Mae T. Pablito | F72: Journal | G72: JOURNAL OF MULTIDISCIPLINARY RESEARCH AND DEVELOPMENT| ISSN 3031-9390Vol. 2, No. 2, 2025, 131-142 | H72: Peer-reviewed | I72: Systematic literature review,English grammar,English proficiency,Undergraduate,ASEAN | J72: https://doi.org/10.56916/jmrd.v2i2.1120
A73: 32 | B73: Jan to June 2025 | C73: CPAG | D73: Enhancing Electoral Integrity: A Comparative Analysis of Electoral Processes in Selected Provinces of Cordillera Administrative Region (CAR), Philippines | E73: Julie M. Binaldo-Velasco | F73: Journal | G73: Social Science Lens: A World Journal of Human Dynamics and Social Relations | H73: Peer-reviewed | I73: Punctuated Equilibrium Theory; Electoral Practices; Peaceful Elections; Cordillera Administrative Region, Voter Awareness | J73: https://doi.org/10.62718/vmca.ssl-wjhdsr.5.1.SC-0525-023
... A91: 50 | B91: July to Dec 2025 | C91: CTE | D91: Gender Treatment in Philippine Commercial Elementary Science Textbooks | E91: Apler J. Bansiong, Emill M. Kisim, Terrilyn G. Dontogan, Albert S. Bolcio Jr. | F91: Journal | G91: MIER Journal of Educational Studies Trends and Practices, 15(2), 326–350. | H91: Web of Science | I91: Gender-responsive pedagogy, Liberal feminist theory, Gender-bias, Sience textbooks, Elementary Level | J91: https://doi.org/10.52634/mier/2025/v15/i2/2869
A92: 51 | B92: July to Dec 2025 | C92: CTE | D92: Teacher Education Graduates' Workplace Behaviors: An Employer Feedback-Generated Taxonomy | E92: Esper Lawig Feliciano | F92: Journal | G92: Journal Of Curriculum Studies Research, 7(2), 443-465. | H92: Scopus | I92: Teacher education employer feedback workplace behavior task and contextual performance Philippine Professional Standards for Teachers disposition-focused development | J92: https://doi.org/10.46303/jcsr.2025.29 | L92: https://www.scopus.com/sourceid/21101155951
A93: 92 | B93: July to Dec 2025 | C93: CN | D93: A 24-Hour Duty Time-Use Analysis: How Much Time Nursing Students Spent Before, During and After Pediatric Clinical Duty. | E93: Jude L. Tayaben | F93: Journal | G93: Studies in health technology and informatics | H93: Scopus | I93: EMR; nursing informatics; pedagogy; time-use analysis | J93: https://doi.org/10.3233/SHTI251162
A94: 93
A95: 94
A96: 95
A97: 96 | B97: Prepared by: Noted by: NOEL A. LENGUAJE, REPO Staff CHERYLL C. LAUNIO, REPO Director
A98: 51
A99: 52
A100: 53
A101: 54
A102: 55
A103: 56
A104: 57
A105: 58
A106: 59
A107: 60
A108: 61
A109: 62
... A117: 70
A118: 71 | B118: July to Dec 2025 | C118: CN | D118: Meaningful Use of Social Media, Information Technology, and Applications in Nursing Education: A Multi-Site, Cross-Sectional Study Among Senior Nursing Students | E118: Jude L Tayaben | F118: Book | G118: Studies in Health Technology and Informatics | I118: Nursing education; nursing informatics; pedagogy | J118: https://ebooks.iospress.nl/doi/10.3233/SHTI251344
A119: 72 | D119: A 24-Hour Duty Time-Use Analysis: How Much Time Nursing Students Spent Before, During and After Pediatric Clinical Duty | E119: Jude L Tayaben | F119: Book | G119: Studies in Health Technology and Informatics | I119: EMR; nursing informatics; pedagogy; time-use analysis | J119: https://ebooks.iospress.nl/doi/10.3233/SHTI251162

Sheet Data_2024
A1: No. | B1: Year | C1: College/Institute | D1: Title | E1: Author(s) | F1: Pub Type | G1: Journal/Book | H1: Category | I1: Keywords | J1: URL | K1: Citations | L1: Remarks
A2: 1 | B2: Jan to June 2024 | C2: CAH | D2: Message patterns through discourse analysis on the concept of apology and forgiveness during Ramadan among college students practicing Islam | E2: Jason V. Chavez, Jhordan T. Cuilan, Haydee G. Adalia | F2: Journal | G2: Environment and Social Psychology | H2: Scopus 2019 to present | I2: communication; apologizing; forgiveness; Islamic beliefs; Ramadan | J2: https://esp.apacsci.com/index.php/esp/article/view/2043 | K2: https://scholar.google.com/citations?view_op=view_citation&hl=en&user=Y5Ot_3wAAAAJ&citation_for_view=Y5Ot_3wAAAAJ:IjCSPb-OGe4C
A3: 2 | B3: Jan to June 2024 | C3: CAH | D3: Gender mainstreaming campaign as a casualty of the online gender-based humor: A discourse analysis | E3: Jason V. Chavez, Jhordan T. Cuilan | F3: Journal | G3: Environment and Social Psychology | H3: Scopus 2019 to present | I3: cultivation; discourse markers; gender-based humor; gender mainstreaming; message patterns; social media | J3: https://esp.apacsci.com/index.php/esp/article/view/2044 | K3: https://scholar.google.com/citations?view_op=view_citation&hl=en&user=Y5Ot_3wAAAAJ&citation_for_view=Y5Ot_3wAAAAJ:UeHWp8X0CEIC
A4: 3 | B4: Jan to June 2024 | C4: CHET/FSRIC | D4: Phenolic-rich lees from Philippine rice wine (tapuy) increases Caenorhabditis elegans lifespan in spite of having low antioxidant activity | E4: Sean Philippe L. Chua, Lesley Dale Umayat & Paul Mark B. Medina | F4: Journal | G4: Food Production, Processing and Nutrition 6:1, 1-12. | H4: Scopus 2019 to present; Clarivate (Emerging Sources Citation Index) | I4: Rice wine, Tapuy, Lees Lifespan, Caenorhabditis elegans, Fermented food | J4: https://doi.org/10.1186/s43014-023-00181-w | K4: https://scholar.google.com/citations?view_op=view_citation&hl=en&user=dVCbH7cAAAAJ&cstart=20&pagesize=80&citation_for_view=dVCbH7cAAAAJ:epqYDVWIO7EC
A5: 4 | B5: Jan to June 2024 | C5: CTE | D5: Pathways to a Succesful Career: Unveiling the PostGraduate Journey – A Tracer Study | E5: Imelda G Parcasio, Russell B Dolendo, Brenda A Langaoen, Percyveranda A Lubrica | F5: Journal | G5: Social Sciences, Humanities and Education Journal | H5: Open Access Peer-reviewed | I5: Educational Management, Employment, Professional Growth, Curricular Activities | J5: http://doi.org/10.25273/she.v5i1.19223 | K5: https://scholar.google.com/citations?view_op=view_citation&hl=en&user=WHPuq_QAAAAJ&citation_for_view=WHPuq_QAAAAJ:Y0pCki6q_DkC
A6: 5 | B6: Jan to June 2024 | C6: CF | D6: Impacts of the COVID-19 Pandemic on Livelihood Assets of Smallholder Agroforestry Farmers in Selected Upland Farming Communities in the Philippines | E6: Leila Landicho, Kenneth A. Laruan, Mary Anne G. Abadillos and Romnick S. Pascua | F6: Journal | G6: Forest and Society, Vol. 8 No. 1 | H6: Scopus 2017 to present; Clarivate (ESCI) | I6: Smallholder, COVID-19, Pandemic, Agroforestry, Philippines | J6: https://doi.org/10.24259/fs.v8i1.28095 | K6: https://scholar.google.com/citations?view_op=view_citation&hl=en&user=PyO6wrQAAAAJ&citation_for_view=PyO6wrQAAAAJ:Y0pCki6q_DkC
A7: 6 | B7: Jan to June 2024 | C7: CF | D7: Generating Wall-to-Wall Canopy Height Information from Discrete Data Provided by Spaceborne LiDAR System | E7: Nova D. Doyog, Chinsu Lin | F7: Journal | G7: Forest Volume 15 No. 3, 482 | H7: Scopus 2010 to Present; Clarivate (Science Citation Index Expanded) | I7: integrated RS- and ML-based canopy height modeling; GEDI; ICESat-2; SAR; challenges in canopy height modeling | J7: https://doi.org/10.3390/f15030482 | K7: https://scholar.google.com/citations?view_op=view_citation&hl=en&user=-WSRHRgAAAAJ&citation_for_view=-WSRHRgAAAAJ:UebtZRa9Y70C
A8: 7 | B8: Jan to June 2024 | C8: ULIS | D8: Information Sources Preferred by Students in Academic Writing | E8: Noel W. Cabfilan | F8: Journal | G8: DESIDOC Journal of Library & Information Technology, Vol. 44, No. 1, | H8: Scopus from 2012 to Present; Clarivate (Emerging Sources Citation Index) | I8: Information sources; Library resources; Online resources; Print resources | J8: https://doi.org/10.14429/djlit.44.1.18909 | K8: https://scholar.google.com/citations?view_op=view_citation&hl=en&user=eRYjj_cAAAAJ&citation_for_view=eRYjj_cAAAAJ:2osOgNQ5qMEC
A9: 8 | B9: Jan to June 2024 | C9: CNS | D9: Development of endemicity and conservation importance indices for tropical forests and the floral diversity assessment of Mt. Natoo in Benguet, Philippines | E9: Johndale Rein T. Bullong, Jim P. Silverio, Joanna I. Alafag, Maricel A. Guron & Jones T. Napaldet | F9: Journal | G9: Journal of Mountain Science Volume 21, pages 428–446 | H9: Scopus from 2007 to Present/Clarivate (SCIE) | I9: Endemicity index, Conservation importance index, Cordillera Central Range, Floristic element, Jaccard Index of Similarity, | J9: https://doi.org/10.1007/s11629-023-8387-9 | K9: https://scholar.google.com/citations?view_op=view_citation&hl=en&user=SCSvSk0AAAAJ&citation_for_view=SCSvSk0AAAAJ:2osOgNQ5qMEC
A10: 9 | B10: Jan to June 2024 | C10: CNS | D10: Application of microorganisms for cross-protection against biotic and metal-induced oxidative stresses in plants | E10: Sherlyn C. Tipayno | F10: Chapter in a Book | G10: Beneficial Microbes for Sustainable Agriculture Under Stress Conditions Functional Traits and Regulation 2024, Pages 201-213 | J10: https://doi.org/10.1016/B978-0-443-13193-6.00011-7 | K10: https://scholar.google.com/citations?view_op=view_citation&hl=en&user=mRtnrlsAAAAJ&citation_for_view=mRtnrlsAAAAJ:7PzlFSSx8tAC
A11: 9 | B11: Jan to June 2024 | C11: CAH | D11: Investigating The Relationship Between Leadership, Self-Efficacy, And Research Productivity In Educational Settings | E11: Fahad A. Salendab, Peter B. Rama Jr, Robert F. Galindez, Dr. Cinder Dianne L. Tabiolo, Norman P. Romasanta, Adamson N. Labi, Leonilo B. Capulso | F11: Journal | G11: Migration Letters Volume: 21, No: S3 (2024), pp. 856-873 | H11: Open access peer-reviewed Scopus from 2011 to 2022 (coverage discontinued in Scopus) not in Clarivate database | I11: Leadership characteristics, Research self-efficacy, Research productivity, Educational settings, Philippines | J11: https://migrationletters.com/index.php/ml/article/view/6869/4558
A12: 11 | B12: Jan to June 2024 | C12: BSU-Buguias | D12: LEADERSHIP STYLE PREFERENCES OF BSU-BUGUIAS CAMPUS FACULTY AND STAFF | E12: Elizabeth M. Bay-an, Jayne B. Miranda, Princess Irene B. Patacsil, Lemar A. Ablasa | F12: Journal | G12: Ignatian International Journal for Multidisciplinary Research Vol 2 No 3 | H12: Open Access Peer-reviewed | I12: leadership style, preferences, Laissez-faire, Democratic, Transactional | J12: https://doi.org/10.5281/zenodo.10890234
A13: 12 | B13: Jan to June 2024 | C13: BSU-Buguias | D13: COPING MECHANISMS IN THE NEW MODALITIES OF TEACHING IN PUBLIC ELEMENTARY SCHOOLS | E13: Lemar A. Ablasa and Genevieve N. Olban | F13: Journal | G13: Ignatian International Journal for Multidisciplinary Research Vol 2 No 2 | H13: Open Access Peer-reviewed | I13: Innovation, platforms, mutual learning, standard hygiene, cognitive appraisal, challenges, stressful job | J13: https://doi.org/10.5281/zenodo.10701774
A14: 13 | B14: Jan to June 2024 | C14: BSU-Buguias | D14: EFFECTIVE APPROACHES EMPLOYED BY ELEMENTARY TEACHERS IN CHRISTIAN SCHOOLS | E14: Lemar A. Ablasa, Janice O. Bagano | F14: Journal | G14: Ignatian International Journal for Multidisciplinary Research Vol 2 No 2 | H14: Open Access Peer-reviewed | I14: Best practices, strategies, differentiated instruction, factors, controllable, physical stamina | J14: https://doi.org/10.5281/zenodo.10719955
A15: 14 | B15: Jan to June 2024 | C15: BSU-Buguias | D15: PARENTS LIVED EXPERIENCES AS STUDY BUDDY OF LEARNERS IN THE NEW NORMAL | E15: Lemar A. Ablasa, Janice K. Bagano and Flordeliza D. De Guzman | F15: Journal | G15: Ignatian International Journal for Multidisciplinary Research Vol 2 No 3 | H15: Open Access Peer-reviewed | I15: COVID-19 pandemic, parental skills, guiding time learning moments, study buddy, roles, formal education | J15: https://doi.org/10.5281/zenodo.10781887
A16: 15 | B16: Jan to June 2024 | C16: BSU-Bokod | D16: Dissemination of the Vision, Mission, Goals, and Objectives of Urdaneta City University: Ethical Implications to Integrity, Teamwork, Competence and Transcendence | E16: Gleemoore C. Makie | F16: Journal | G16: International Journal Of Empirical Research Methods Volume 2, Issue 1, PP: 53-71 | H16: Open Access Peer-reviewed | I16: Extent, Dissemination, Vision, Mission, Goal, Objectives | J16: https://www.guinnesspress.org/assets/articles/pdf/ijerm-v2-5-52471-Gleemoore-C.-Makie.pdf
A17: 10 | B17: Jan to June 2024 | C17: CAH | D17: A SCOPING REVIEW OF LANGUAGE PROGRAMS AND POLICIES IN ASEAN COUNTRIES | E17: Alexee Jaezhelle C. Pugong, John Rey Osben Pelila, Matin Evony P. Moling, Jocel T. Dolo, Norhana A. Usman | F17: Journal | G17: Indonesian Journal of Research and Educational Review Volume 3, No. 2, 2024, pp 82-102 | H17: Open Access Peer-reviewed | I17: ASEAN Countries; Languge; Programs and Policies; Scoping Review | J17: https://doi.org/10.51574/ijrer.v3i2.1181 | K17: https://scholar.google.com/citations?view_op=view_citation&hl=en&user=mi5aC-4AAAAJ&citation_for_view=mi5aC-4AAAAJ:W7OEmFMy1HYC
A18: 11 | B18: Jan to June 2024 | C18: CE | D18: Impact of using glucose as a sole carbon source to analyze the effect of biochar on the kinetics of biomethane production | E18: Valentin, M.T., Białowiec, A | F18: Journal | G18: Scientific Reports | H18: Clarivate (Web of Science -SCIE); Scopus from 2011 to present | I18: Biochar, Glucose, Kinetics, Digestion, Biomethane | J18: https://doi.org/10.1038/s41598-024-59313-y | K18: https://scholar.google.com/citations?view_op=view_citation&hl=en&user=8_fUSUcAAAAJ&citation_for_view=8_fUSUcAAAAJ:0EnyYjriUFMC
A19: 12 | B19: Jan to June 2024 | C19: BSU-Bokod | D19: Poetic Justice, Love, and Womanhood | E19: Gleemore Makie, Christopher Ryan Maboloc | F19: Journal | G19: Social Ethics Society Journal of Applied Philosophy Special Issue, February 2024, 280-291 | H19: Open Access Peer-reviewed | I19: Radicalism; Rodrigo Duterte; Poetry, Ideal Love; Women | J19: https://ses-journal.com/wp-content/uploads/2024/03/SES-Journal_Special-Issue_Feb-2024_Article-13_final-1.pdf | K19: https://scholar.google.com/citations?view_op=view_citation&hl=en&user=GaRs-FgAAAAJ&cstart=20&pagesize=80&citation_for_view=GaRs-FgAAAAJ:uWQEDVKXjbEC
A20: 13 | B20: Jan to June 2024 | C20: CAH | D20: Pinoylish: The Awareness and Notions of University Students in Northern Luzon | E20: Joseph B. Quinto | F20: Journal | G20: TEFLIN Journal, Volume 35, Number 1, 2024 | H20: ASEAN Citation Index but articles uploaded until 2022 only Scopus from 2018 to 2023 only | I20: English language teaching, Philippine English, Pinoylish, pluricentric model | J20: http://dx.doi.org/10.15639/teflinjournal.v35i1/107-122 | K20: https://scholar.google.com/citations?view_op=view_citation&hl=en&user=hTEK3WYAAAAJ&citation_for_view=hTEK3WYAAAAJ:Se3iqnhoufwC
A21: 14 | B21: Jan to June 2024 | C21: CTE/HERRC | D21: Alumni’s Retrospective Evaluation of their Undergraduate Secondary Teacher Education Training | E21: Apler J. Bansiong and Dolores Alawas | F21: Journal | G21: Mountain Journal of Science and Interdiciplinary Research | H21: Scopus | I21: 21st-century skills, Alumni feedback, Retrospective evaluation by alumni, Graduate tracer study, curriculum, Physical resources | J21: http://portal.bsu.edu.ph:8083/index.php/BRJ/article/view/400/418 | K21: https://scholar.google.com/citations?view_op=view_citation&hl=en&user=Y3vamKYAAAAJ&citation_for_view=Y3vamKYAAAAJ:LkGwnXOMwfcC
A22: 15 | B22: Jan to June 2024 | C22: IFHSA | D22: Fungal Contaminants and Cup Quality of Stored Roasted Arabica Coffee | E22: Von Y. Amado, Andres A. Basalong, And Hazen Lyn B. Talbino | F22: Journal | G22: Mountain Journal of Science and Interdiciplinary Research | H22: Scopus | I22: Arabica coffee, storage, microbial contamination, cup quality | J22: http://portal.bsu.edu.ph:8083/index.php/BRJ/article/view/397/415
A23: 16 | B23: Jan to June 2024 | C23: CAH | D23: The Use of Podcasts for Language Learning: A Systematic Review of Literature | E23: Michaela G. Ramirez | F23: Journal | G23: International Journal of English Language Studies | H23: Scopus | I23: Podcasts, language, learning, benefits, drawbacks, roles of podcast, systematic review | J23: https://doi.org/10.32996/ijels.2024.6.1.4
A24: 17 | B24: Jan to June 2024 | C24: CA | D24: Verification on Energy Digestibility in Ground Yellow Corn, Rice Bran, and Copra Expeller Fed to 10 to 15 kg Benguet Native Pigs | E24: Mineralito F. Simon and Mary Arnel D. Garcia | F24: Journal | G24: Mountain Journal of Science and Interdiciplinary Research | H24: Scopus | I24: digestibility trial, feeding standard, indigenous pig, nutrition, feed ingredients | J24: http://portal.bsu.edu.ph:8083/index.php/BRJ/article/view/398/416
A25: 18 | B25: July to December 2024 | C25: CF | D25: Cultural and Spiritual Adaptations to Extreme Weather Events of Ethnic Farming Communities of the Three Watersheds Situated at Different Altitudinal Locations along Agno River Basin, Benguet and Pangasinan, Philippines | E25: Josel M. Florentin and Emerson V. Barcellano | F25: Journal | G25: Vol. 2 No. 4 (2024): European Journal of Theoretical and Applied Sciences | H25: Open access peer-reviewed | I25: Agno River Basin, Ethnic farming communities, Cultural/spiritual adaptations, extreme weather, climate- related hazards | J25: https://doi.org/10.59324/ejtas.2024.2(4).14
A26: 19 | B26: July to December 2024 | C26: CNS | D26: Ecological insights on communal forests in the tropics: The case of Alapang Communal Forest of La Trinidad, Benguet, Philippines | E26: Marvin P. POCYOY, Jones T. NAPALDET | F26: Journal | G26: Taiwania | H26: SCOPUS/ Clarivate/ Web of Science (ISI) | I26: carbon stock, community perspective, depressed station, Pinus kesiya, urban communal forest. | J26: https://www.researchgate.net/profile/Jones-Napaldet/publication/382889888_Ecological_insights_on_communal_forests_in_the_tropics_The_case_of_Alapang_Communal_Forest_of_La_Trinidad_Benguet_Philippines/links/66b21fdd51aa0775f26d7ef5/Ecological-insights-on-communal-forests-in-the-tropics-The-case-of-Alapang-Communal-Forest-of-La-Trinidad-Benguet-Philippines.pdf
A27: 20 | B27: July to December 2024 | C27: CF | D27: Indigenous Ecological Knowledge and Systems of Ethnic Farmers Located at Different Altitudinal Locations along Agno River, Philippines | E27: Josel M. Florentin and Emerson V. Barcellano | F27: Journal | G27: American Journal of Agricultural Science, Engineering, and Technology | H27: Open access peer-reviewed | I27: Climate Stressors, Ethnic Communities, Farming Techniques, Indigenous Knowledge and Systems, Watershed | J27: https://doi.org/10.54536/ajaset.v8i3.3347
A28: 21 | B28: July to December 2024 | C28: CNS | D28: Self-purification in tropical upland rivers as affected by environmental factors: the case of Balili River in Benguet, Philippines | E28: Mercedes K. Ago,Regine D. Caasi,Divina S. Kege-e &Jones T. Napaldet | F28: Journal | G28: International Journal of Phytoremediation | H28: Scopus 1994, from 1996 to 2024, WoS (Science Citation Index Expanded) | I28: Canonical correspondence analysis, elevation, floral diversity, natural regeneration | J28: https://doi.org/10.1080/15226514.2024.2380751
A29: 22 | B29: Jan to June 2024 | C29: CIS | D29: 8-Week Self-Training Program in Sepak Takraw | E29: Dustin Paolo Tinte Cruz, Russell B. Dolendo | F29: Journal | G29: Puissant | H29: Open access peer-reviewed | I29: quasi-experimental, physical fitness, training program, athletes, performances | J29: https://www.puissant.stepacademic.net/puissant/article/view/403
A30: 23 | B30: July to December 2024 | C30: CA | D30: Genetic diversity and population structure of Philippine strawberry germplasm based on genome-wide simple sequence repeat markers | E30: Elec VH, Cadorna CAE, Tad-Awan BA, Basquial DA, Dumaslan MR, Rey JD | F30: Journal | G30: Biodiversitas | H30: Clarivate (Zoological records)/Scopus from 2014 to present/ACI | I30: dmixture, genetic diversity, geographic origin, Philippine strawberry, SSRs | J30: https://smujo.id/biodiv/article/view/17437
A31: 24 | B31: Jan to June 2024 | C31: CHET | D31: PO-MU-MA Emergency food bar: nutritional, microbial, sensorial, and cost analysis | E31: Lyka Mae Socao Ibayan Frenzel May Diano Bauding Maxyne Piper Salupen Cabading Bernadette Manuel Cayabyab Pelin Bugtong Belino | F31: Journal | G31: Brazilian Journal of Development | H31: Open access peer-reviewed | I31: emergency food bar, potato, mung bean, malunggay | J31: https://doi.org/10.34117/bjdv10n6-065
A32: 25 | B32: July to December 2024 | C32: CPAG | D32: From Social Media Engagement to Voting Decisions: Influence of Social Media on Local Election | E32: John Wilson C. Nicolas; Renebeth G. Donguiz | F32: Journal | G32: Cognizance Journal of Multidisciplinary Studies | H32: Open access peer-reviewed | I32: Social media engagement, voting behavior, voting decisions, voter turnout | J32: https://d1wqtxts1xzle7.cloudfront.net/117047837/V4I705-libre.pdf?1722010120=&response-content-disposition=inline%3B+filename%3DFrom_Social_Media_Engagement_to_Voting_D.pdf&Expires=1728614860&Signature=gJciSO6jNJGkz3hrJIvoUiRjdY2t5A05Il5dlRTLSEjPnLtlX7xnX-p4fMrbBeWstBQR3fRWcUV6BWjw62f8N8w~ZYIqlCQiJdiQRYkScygVGQkuerVGugG9p~wVYX-SKVaROzFPoAWpGTUz7q-KnofEYHhwDQJHp48tzY8tsrsm04~C-MCh9tqfm5IAgRRJvT4PkCtMMfFmSNUoYn76tJF7qncEHhJXOA3oX1hfrmz6FtPKH9YXgI2vfYtgXnPChbrY~2Jzxrg~XjQoEkQJlEc2C4LHqll-8MTzYnsc-Xg8VmF6QWQiELizOmS~z67LdOvFUPlPPkTg4FiT7iK1MQ__&Key-Pair-Id=APKAJLOHF5GGSLRBV4ZA
A33: 26 | B33: July to December 2024 | C33: CAH | D33: Self-efficacy in communication and employability skills of English language students | E33: Joerene Mae Layagan | F33: Journal | G33: ELT Forum: Journal of English Language Teaching | H33: Open access peer-reviewed | I33: employability, English language students, employable skills, written communication skills, oral communication skills | J33: https://doi.org/10.15294/elt.v13i2.1516
... A35: 28 | B35: July to December 2024 | C35: CAH | D35: Internship Experience: The MMMAPS, the WorST, and the Interns | E35: Joseph B. Quinto, Frances Mae G. Diase | F35: Journal | G35: Informasi | H35: Open access peer-reviewed | I35: career trajectories, hurdles, internship experience, CMO number 35, series of 2017 | J35: https://scholarhub.uny.ac.id/informasi/vol54/iss1/1/
A36: 29 | B36: Jan to June 2024 | D36: Methods Used in YouTube for Teaching and Learning English Language: A Systematic Literature Review | E36: Rufino, Gilliane G. | F36: Journal | G36: International Journal of English Language Studies, 6(1), 82–97. | H36: Scopus from 2019 to 2024 | I36: YouTube, English Learning, Audio-Visual | J36: https://doi.org/10.32996/ijels.2024.6.1.9%20
A37: 30 | B37: July to December 2024 | C37: CAH | D37: Pragmatic Instructions in Oral Communication in Context | E37: Joseph B Quinto | F37: Journal | G37: JLE: Journal of Literate of English Education Study Program, 5(1), 1-16. | H37: Open access peer-reviewed | I37: interlanguage pragmatics, oral communication in context, pragmatic instructions | J37: https://doi.org/10.47435/jle.v5i1.2952
A38: 31 | B38: July to December 2024 | C38: CAH | D38: The Dichotomy of Thumbs-Up Emoji in Online Conversations | E38: John Rey Osben Pelila, Jayson Ace Kigis Abenoja, Troy Pangwi Raymundo | F38: Journal | G38: INDONESIAN JOURNAL OF EDUCATIONAL RESEARCH AND REVIEW Volume 7 Nomor 2 2024, pp 347-356 | H38: Open access peer-reviewed | I38: Emoji, Komunikasi Online, Tinjauan Literatur Sistematis | J38: https://doi.org/10.23887/ijerr.v7i2.75698
A39: 32 | B39: Jan to June 2024 | C39: CPAG | D39: Application Of The Levinisian Face-To-Face Dialogue Among Local Government Units: Basis Of Trendsetting Organizational Communication | E39: Renebeth Gatudan Donguiz | F39: Journal | G39: Cultural Landscape Insights | H39: Open access peer-reviewed | I39: Organizational Communication Levinas Face-To-Face Dialogue Organizational Change | J39: https://doi.org/10.59762/cli901324532120240305153643
A40: 33 | B40: July to December 2024 | C40: ULIS | D40: A Bibliometric Analysis of Benguet State University Research Journals (1977–2023): Implications for Library Resource Acquisitions, Access, and Services | E40: Daniel S. Balbin Jr. | F40: Journal | G40: Science & Technology Libraries | H40: Scopus from 1980 to 2008, from 2010 to 2024 | I40: Bibliometric analysislibrary accesslibrary acquisitionperformance analysisresearch productivityscience mapping | J40: https://doi.org/10.1080/0194262X.2024.2434836
A41: 34 | B41: July to December 2024 | C41: CAH | D41: In What Ways Do Educators Respond to Plagiarism Among Students? | E41: John Rey Osben Pelila, Johnell B. Desalit, Bernadette L. Soliba | F41: Journal | G41: Indonesian Journal of Research and Educational Review | H41: Open access peer-reviewed | I41: Higher Education, Philippines, Plagiarism, Output-Based Assessment | J41: https://doi.org/10.51574/ijrer.v3i4.1971
A42: 35 | B42: July to December 2024 | C42: CIS | D42: Telemedicine Adoption in Developing Economies: A Systematic Review on the Enablers and Barriers Review on the Enablers and Barrie | E42: Zaidbren Macabato1, Lemuel Clark Velasco1-3, Art Brian Escabarte4, Mae-Lanie Poblete4*, Armando Isla Jr.5, Rentor Cafino6, Sarah Lizette Aquino-Cafino7, Frevy Teofilo-Orencia8 | F42: Journal | G42: Kesmas: Jurnal Kesehatan Masyarakat Nasional (National Public Health Journal) | H42: Scopus from 2016 to 2024 | I42: barriers, enablers, technology adoption, telehealth, telemedicine | J42: https://doi.org/10.21109/kesmas.v19i4.1343
A43: 36 | B43: July to December 2024 | C43: CF | D43: Applying a Four-Way Factorial Experimental Model to Diagnose Optimum kNN Parameters for Precise Aboveground Biomass Mapping | E43: Chinsu Lin; Nova D. Doyog | F43: Journal | G43: IEEE Journal of Selected Topics in Applied Earth Observations and Remote Sensing ( Volume: 18) | H43: Scopus:from 2008 to 2024, WoS (Science Citation Index Expanded) | I43: Forestry;Biological system modeling;Estimation;Biomass;Measurement;Uncertainty;Systematics;Random forests;Carbon;Sampling methods;Adaptable precision management;Airborne laser scanning (ALS) lidar;carbon accounting;forest degradation;information uncertainty;k-nearest neighbor (kNN) approach estimated AGB (kNN-AGB) modeling;sampling scheme}, | J43: https://doi.org/10.1109/JSTARS.2024.3486737
A44: 37 | B44: July to December 2024 | C44: CA | D44: Black Soldier Fly (Hermetia illucens L.) Larval Development as Affected by Different Substrates | E44: Septer Sucdad | F44: Journal | G44: Andalasian International Journal of Entomology, | H44: Open access peer-reviewed | I44: Black Soldier Fly,Cabbage Trimmings,Banana Peelings,Retrograded Rice | J44: https://doi.org/10.25077/aijent.2.2.114-121.2024
A45: 38 | B45: Jan to June 2024 | C45: CAH | D45: Mirroring academic journeys through figurative language in the Book of Proverbs | E45: Jonathan Marcos Macaraeg 1,2,* , John Rey Osben Pelila 1,3, and Joselito C. Gutierrez 1 | F45: Journal | G45: Cambodian Journal of Educational Research | H45: Open access peer-reviewed | I45: Book of Proverbs; figurative language; figure of speech; values; Bible-based English language teaching | J45: https://www.researchgate.net/profile/John-Rey-Pelila/publication/382802211_Mirroring_academic_journeys_through_figurative_language_in_the_Book_of_Proverbs/links/66acd5f02361f42f23aefba6/Mirroring-academic-journeys-through-figurative-language-in-the-Book-of-Proverbs.pdf
A46: 39 | B46: July to December 2024 | C46: CNS | D46: Water quality of Balili River before, during and after COVID: lessons learned and ways forwards for tropical river remediation | E46: Fernie D. SitSit, Romeo M. Dizon & Jones T. Napaldet | F46: Journal | G46: Aquatic Ecology | H46: Scopus:from 1996 to 2024; WoS (Science Citation Index Expanded) | I46: Self-purification COVID Water quality Water quality index Balili River | J46: https://doi.org/10.1007/s10452-024-10151-0
A47: 40 | B47: July to December 2024 | C47: CAH | D47: Parental Discretionary Influence on Their Children’s Manner of Learning English Language | E47: Noel A. Comeros 1 , Jhordan T. Cuilan 2 , Jason V. Chavez 3 | F47: Journal | G47: Forum for Linguistic Studies | Volume 06 | Issue 04 | H47: Scopus:from 2019 to 2024; | I47: Parental discretionary; Influence on their children’s manner; Learning English language | J47: https://www.researchgate.net/profile/Jhordan-Cuilan/publication/384881042_Parental_Discretionary_Influence_on_their_Children's_Manner_of_Learning_English_Language/links/670bb8c4dc91726ad38e570f/Parental-Discretionary-Influence-on-their-Childrens-Manner-of-Learning-English-Language.pdf
A48: 41 | B48: July to December 2024 | C48: CTE | D48: Differential Treatment of Science, Technology, and Society Themes in the Philippine Junior High School Science Curriculum | E48: Bansiong, A., Ocampo, R. F., Caluza, E. M. V., & Rillera, M. B. | F48: Journal | G48: Diversitas Journal ISSN 2525-5215 Volume 9, Issue 4 | H48: Open access peer-reviewed | I48: science textbooks, science teachers, human health and diseases, air quality , atmosphere | J48: https://doi.org/10.48017/dj.v9i4.3132
A49: 42 | B49: July to December 2024 | C49: CE | D49: Influence of inoculum-to-substrate ratio on biomethane production via anaerobic digestion of biomass | E49: Marvin T. Valentin, Daniel Ciolkosz, Andrzej Białowiec | F49: Journal | G49: Environmental Microbiology Reports Volume 16, Issue 6 | H49: Scopus:from 2009 to 2024; WoS (Science Citation Index Expanded) | J49: https://doi.org/10.1111/1758-2229.70009
A50: 43 | B50: July to December 2024 | C50: CNS | D50: Social work students’ perspectives on the future of human rights | E50: Marcin BoryczkoORCID Icon,Melinda MadewORCID Icon,Mark Lusk &Jason LeungORCID Icon | F50: Journal | G50: Social Work Education | H50: Scopus:from 1981 to 2024; WoS (Emerging Sources Citation Index) | I50: Human rightssocial workenvironmental rightscollective rightsauthoritarian nationalism | J50: https://doi.org/10.1080/02615479.2024.2415994
A51: 44 | B51: Jan to June 2024 | C51: CAH | D51: Navigating Covid-19 Challenges – How Physical Education Teachers Skillfully Applied Their Expertise | E51: Dennis Mokyat Daw-as a, *, John Rey Osben Pelila | F51: Journal | G51: International Journal of PHYSICAL EDUCATION, FITNESS AND SPORTS | H51: Open access peer-reviewed | I51: Distance learning education, Online education, Systematic literature review, Philippines | J51: https://ijpefs.org/index.php/ijpefs/article/view/560
A52: 45 | B52: July to December 2024 | C52: ISRD | D52: Motivating Factors and Challenges of Faculty Members in a State University in the Philippines in Publishing Journal Articles | E52: Cheryll Casiwan Launio, Freda Kate Damoslog Samuel, Alladin Banez, Matyline Camfili Talastas, Leonila Sito, Kristine Baniqued Dela Cruz | F52: Journal | G52: Journal of Scientometric Research, 2024; 13(3):866-876. | H52: Scopus from 2019 to 2024, WoS (Emerging Sources Citation Index) | I52: Research productivity metrics, Journal publication rate, Motivation to publish, Faculty researcher determinants, Publishing journal articles | J52: https://jourdata.s3.us-west-2.amazonaws.com/jscires/JScientometRes-13-3-866.pdf
A53: 46 | B53: Jan to June 2024 | C53: CE | D53: Development of a cell-type cylindrical carrot seeder | E53: Marvin T. Valentin, Keithler M. Pagnas ∙ Roger Lee M. Suclad ∙ Algirdas Jasinskas ∙ Rolandas Domeika ∙ Egidijus Šarauskis | F53: Journal | G53: Heliyon | H53: Scopus from 2015 to 2024; WoS (Science Citation Index Expanded) | I53: Seeder Cylindrical Carrot Hill center Operating speed | J53: https://doi.org/10.1016/j.heliyon.2024.e39605
A54: 47 | B54: July to December 2024 | C54: CNS | D54: Anti-Hypertensive and Anti-Hypercholesterolemic Effects of Protein Hydrolysates from (Phaseolus vulgaris) L. in Functional Beverage | E54: Yvonne D. Bolayo*, Mary Ann O. Torio | F54: Journal | G54: Jurnal Gizi dan Pangan (Indonesian Journal of Nutrition and Food), July 2024, 19(2):107-116 | H54: WoS (Emerging Sources Citation Index) | I54: anti-hypertensive, anti-cholesterolemic, bioactive peptides, common beans, functional beverage | J54: https://doi.org/10.25182/jgp.2024.19.2.107-116
A55: 48 | B55: July to December 2024 | C55: CAH | D55: Pinoy Tells: The Typology of English Language Learning Strategies | E55: Quinto, J.B. &Cacanindin, M.R. | F55: Journal | G55: Advanced Education, 25. | H55: Scopus from 2020 to 2024; WoS (Emerging Sources Citation Index) | I55: language learning strategies, cross-sectional exploratory sequential design, undergraduate university learners, inventory of English language learning strategies. | J55: https://doi.org/10.20535/2410-8286.309352
A56: 49 | B56: July to December 2024 | C56: CNS | D56: AVIFAUNAL DIVERSITY OF THE NORTHERN CEMENT CORPORATION (NCC) IN SISON, PANGASINAN, PHILIPPINES | E56: Janice P. Balangen, Jocelyn A. Floresca, Johndale Rein T. Bullong and Jones T. Napaldet | F56: Journal | G56: Journal of Wetlands Biodiversity | H56: Open access peer-reviewed (not included in WoS list as of January 2025 | I56: endemics, karst forest, Passer montanus, Pycnonotus goiavier, residents | J56: https://www.researchgate.net/publication/386218511_AVIFAUNAL_DIVERSITY_OF_THE_NORTHERN_CEMENT_CORPORATION_NCC_IN_SISON_PANGASINAN_PHILIPPINES
A57: 50 | B57: July to December 2024 | C57: CNS | D57: FLORAL DIVERSITY AND CARBON STOCK ASSESSMENTS IN THE NATIONAL GREENING PROGRAM (NGP) SITE OF NORTHERN CEMENT CORPORATION (NCC) IN SISON, PANGASINAN | E57: Jennifer C. Paltiyan-Bugtong, Marvin P. Pocyoy, Cleefershel P. Kiligto, Christian Wallace K. David, Johndale Rein T. Bullong and Jones T. Napaldet | F57: Journal | G57: Journal of Wetlands Biodiversity | H57: Open access peer-reviewed (not included in WoS list as of January 2025 | I57: DENR-Philippines, carbon sequestration, diversity indices, NGP goals | J57: https://www.researchgate.net/publication/386219053_FLORAL_DIVERSITY_AND_CARBON_STOCK_ASSESSMENTS_IN_THE_NATIONAL_GREENING_PROGRAM_NGP_SITE_OF_NORTHERN_CEMENT_CORPORATION_NCC_IN_SISON_PANGASINAN
A58: 51 | B58: July to December 2024 | C58: CNS | D58: SPECIES RICHNESS AND RIPARIAN VEGETATION OF UPPER CHICO RIVER IN BONTOC, MOUNTAIN PROVINCE | E58: Lichelyn M. Nasungan, Arel B. Sia-ed and Jones T. Napaldet | F58: Journal | G58: Journal of Wetlands Biodiversity | H58: Open access peer-reviewed (not included in WoS list as of January 2025 | I58: forest, human disturbance, residential, rice field | J58: https://www.researchgate.net/publication/386218927_SPECIES_RICHNESS_AND_RIPARIAN_VEGETATION_OF_UPPER_CHICO_RIVER_IN_BONTOC_MOUNTAIN_PROVINCE
A59: 52 | B59: July to December 2024 | C59: CA | D59: Climate Risk Profiles for a Climate-Resilient Agriculture on Selected Crops in the Cordillera Administrative Region | E59: Janet P. Pablo, Madeline S. Kingan, and Ben P. Sebiano | F59: Journal | G59: Mountain Journal of Science and Interdiciplinary Research | H59: Scopus | I59: Climate hazard, Tropical cyclone, Drought, Food security, Climate resilient technologies | J59: https://doi.org/10.70884/mjsir.v84i2.423
A60: 53 | B60: July to December 2024 | C60: CTE | D60: Issues and Challenges Faced by Pre-Service Teacher-Participants of the SEA Teacher Project of SEAMEO | E60: Imee C. Cuadra, & Ma. Myriam B. Bacud | F60: Journal | G60: Mountain Journal of Science and Interdiciplinary Research | H60: Scopus | I60: SEA Teacher Project, Pre-service teachers, Performance evaluation, Language barriers, Combined research approach | J60: https://doi.org/10.70884/mjsir.v84i2.427
A61: 60
A62: 61 | C62: Prepared by: | D62: NOEL A. LENGUAJE | E62: Noted by: CHERYLL C. LAUNIO
A63: 62 | D63: REPO Staff | E63: REPO Director
A64: 63
A65: 64
A66: 65
A67: 66 | G67: f

Sheet Data_2023
A1: No. | B1: Year | C1: College/Institute | D1: Title | E1: Author(s) | F1: Pub Type | G1: Journal/Book | H1: Category | I1: Keywords | J1: URL | K1: Citations | L1: Remarks
A2: 1 | B2: Jan-June 2023 | C2: CAH | D2: TeachTokerists in the Philippines: A Husserlian Phenomenology | E2: Joseph B. Quinto and Denver M. Cho-oy | F2: Journal | G2: Asia Social Issues | H2: open access peer-reviewed | I2: TikTok, Husserlian phenomenology, TeachTokerists, EduTok, Short-video platform | J2: https://so06.tci-thaijo.org/index.php/asi/article/view/258636/174963
A3: 2 | B3: Jan-June 2023 | C3: CF/GIS | D3: Biomass and Carbon Stock Assessment of Trees in the Lowland Evergreen Forest of Mt. Iraya, Batanes, Philippines | E3: Roscinto Ian C. Lumbres*, Deign Frolley C. Soriano, Nova D. Doyog, Romel A. Raterta, Severino C. Villarta Jr., and Zenaida G. Baoanan | F3: Journal | G3: Philippine Journal of Science | H3: Clarivate (Web of Science - Zoological Records); Scopus from 2009 to present | I3: carbon sequestration, climate change, forest conservation, forest biometry, greenhouse gas, protected area | J3: https://philjournalsci.dost.gov.ph/images/pdf/pjs_pdf/vol152no1/biomass_and_carbon_stock_assessment_of_tress_in_Mt_Iraya_Batanes_.pdf
A4: 3 | B4: Jan-June 2023 | C4: BSU-Bokod | D4: Discourse of culture and ideology in two African novels: Evolving a proto-literacy model | E4: Chester B. Esnara | F4: Journal | G4: Research Journal in Advanced Humanities | H4: Scopus from 2020 to present | I4: Discourse of culture and ideology, proto-literacy model, critical discourse analysis or CDA, processes of transitivity, language-literature interface, African novel | J4: https://royalliteglobal.com/advanced-humanities/article/view/989
A5: 4 | B5: Jan-June 2023 | C5: CE | D5: Investigation of the performance of a cylindrical hopper and metering device of a carrot seeder | E5: Marvin T. Valentin, Andrzej Białowiec, Davut Karayel, Algirdas Jasinskas, Daniel Ciolkosz & Jeffrey A. Lavarias | F5: Journal | G5: Scientific Reports | H5: Clarivate (Web of Science -SCIE); Scopus from 2011 to present | I5: Applied mathematics, Engineering, Mathematics and computing, Mechanical engineering | J5: https://www.nature.com/articles/s41598-022-25798-8
A6: 5 | B6: Jan-June 2023 | C6: CN | D6: Vaccine wastage in the Philippines: An examination of the contributory factors | E6: Gilbert D. Bernardino Jr., Karolyn Rae A. Yogyog, Jude L. Tayaben, Paul Froilan U. Garma | F6: Commentary | G6: Public Health Challenges | H6: Wiley | I6: COVID-19, disinformation, health literacy, public–private partnerships, vaccine hesitancy, vaccinewastage | J6: https://onlinelibrary.wiley.com/doi/epdf/10.1002/puh2.50
A7: 6 | B7: Jan-June 2023 | C7: CF/GIS | D7: Climate risk vulnerability assessment on the production of heirloom rice (Oryza sativa L.) and Arabica coffee (Coffea arabica L.) in Mountain Province, Philippines | E7: Levi Ezekiel O. Daipan, Roscinto Ian C. Lumbres*, Myra Nieves T. Lingaling, Lynn J. Talkasen, Quinerlyn A. Godio, Guillermo A. Mendoza | F7: Journal | G7: SciEnggJ | H7: Clarivate (Web of Science - Zoological Records)/Scopus | I7: Climate risk, vulnerability, heirloom rice, Arabica coffee, exposure, sensitivity, adaptive capacity | J7: https://scienggj.org/2023/SciEnggJ%202023-vol16-no01-p28-39-Daipan%20et%20al.pdf
A8: 7 | B8: Jan-June 2023 | C8: CF | D8: Diversity assessment and listing of birds in Mt. Santo Tomas Forest Reserve in Tuba, Benguet Northern Philippines | E8: G.M. Alfonso | F8: Journal | G8: Israel Journal of Ecology and Evolution | H8: Clarivate (Web of Science -SCIE); Scopus from 2006 to present | I8: birds diversity; richness; evenness; abundance; listing; eco class; endemism; species composition; conservation status | J8: https://doi.org/10.1163/22244662-bja10053
A9: 8 | B9: Jan-June 2023 | C9: CPAG | D9: Developing Finance Strategies: A Narrative on Financial Behavior of a State University Employees | E9: Glorina C. Damong | F9: Journal | G9: International Journal For Multidisciplinary Research | H9: open access peer-reviewed | I9: Financial Behavior, Finance Strategies, Employees | J9: https://www.ijfmr.com/research-paper.php?id=2072
A10: 9 | B10: Jan-June 2023 | C10: CF | D10: Challenges of Retrieving LULC Information in Rural-Forest Mosaic Landscapes Using Random Forest Technique | E10: Chinsu Lin* and Nova D. Doyog | F10: Journal | G10: Forests 2023, 14(4), 816 | H10: Scopus/Clarivate | I10: forest classification; mapping; forest degradation; agriculture; machine learning; sustainability | J10: https://www.mdpi.com/1999-4907/14/4/816
A11: 10 | B11: Jan-June 2023 | C11: CN | D11: Water quality, plankton community and primary productivity of Langiran Lake in Bayambang, Pangasinan, Philippines | E11: Mendoza, Dante M; Aquino, Michelle G B; Tandoc, Mark P; Briñas, Karen B B; Reyes, Doname A; et al. | F11: Journal | G11: AACL Bioflux, 2023, Volume 16, Issue 2. | H11: Scopus | I11: eutrophication, Langiran Lake, phytoplankton, trophic status, zooplankton. | J11: https://www.proquest.com/openview/40c750d5a62fadda32c139bc24378005/1?pq-origsite=gscholar&cbl=2046424
A12: 11 | B12: Jan-June 2023 | C12: CNS | D12: Principal components of students’ difficulties in mathematics in the purview of flexible learning | E12: Sibaen, N. W., Buasen, J. A., & Alimondo, M. S. | F12: Journal | G12: Journal on Mathematics Education, 14(2), 353–37 | H12: Scopus | I12: Flexible LearningMathematicsPrincipal Component AnalysisStudents’ Difficulties | J12: https://doi.org/10.22342/jme.v14i2.pp353-374
A13: 12 | B13: Jan-June 2023 | C13: CNS | D13: Plant Diversity in Selected Agro- and Forest Ecosystems in Indigenous Cultural Communities (ICCs) in the Cordillera Region, Northern Philippines | E13: Romeo A. Gomez Jr, Jason M. Leung, Joyce N. Paing, Elizabeth T. Dom-ogen, Aldrin V. Baniaga & Rey D. Napoleon | F13: Book | G13: Plant Diversity in Biocultural Landscapes | H13: Springer | I13: Indigenous cultural communities (ICCs) Traditional rice-based ecosystems (TRBEs) UNESCO World Heritage GIAHS SEPL Satoyama-satoumi Protected areas Communal | J13: https://link.springer.com/chapter/10.1007/978-981-19-8649-9_22
... A17: 15 | B17: Jan-June 2023 | C17: CAH | D17: Assessment of the Implementation of Mother Tongue Based -Multilingual Education in Benguet | E17: Dominga S. Tomas | F17: Journal | G17: E-DAWA: An International Multidisciplinary Research Journal Volume 3 I Issue 1 I May 2023 | H17: open access peer-reviewed | I17: pagtataya, MTB-MLE, implementasyon, unang wika | J17: https://doi.org/10.56901/FKAE5866
A18: 16 | B18: Jan-June 2023 | D18: Thriving Women After Marital Separation: A Case Study | E18: Erlyn Honeylette C Marquez, Cecilia G Junio | F18: Journal | G18: PSU Journal of Advanced Studies | H18: open access peer-reviewed | I18: Separated Married Women, Thriving Experiences, Challenges, Coping Techniques, Counseling Techniques | J18: https://www.psurj.org/online/index.php/jas/article/view/257
A19: 17 | B19: Jan-June 2023 | C19: CNS | D19: Intensities of human disturbance dictate the floral diversity in tropical forest: the case of a secondary forest in Benguet, Philippines | E19: Domelson A. Balangen, Melchor S. Catones, Jane M. Bayeng & Jones T. Napaldet | F19: Journal | G19: Journal of Mountain Science | H19: Scopus from 2007-2024, Web of Science-SCIE | I19: Land use change Secondary forest Conventional farming Endemic species Exotic species | J19: https://link.springer.com/article/10.1007/s11629-022-7830-7
A20: 18 | B20: Jan-June 2023 | C20: CA | D20: Performance of Seed-Primed Ricebean (Vigna umbellata L.) Using Organic-Based Priming Materials and Priming Duration | E20: Hector C. Gayomba, Belinda A. Tad-awan, Hilda V. Palaes, and Juniel S. Busiguit | F20: Journal | G20: Mountain Journal of Science and Interdisciplinary Research 83 No. 1 | H20: Scopus | I20: organic-based priming materials, seed priming, priming duration, ricebean | J20: http://portal.bsu.edu.ph:8083/index.php/BRJ/article/view/353
A21: 19 | B21: Jan-June 2023 | C21: CHET | D21: Development of Berry-Flavored Lemongrass Herbal Tea | E21: Kathlyn P. Aragon and Jao-jao A. Somyden | F21: Journal | G21: Mountain Journal of Science and Interdisciplinary Research 83 No. 1 | H21: Scopus | I21: Lemongrass, Strawberry, Mulberry, Herbal tea | J21: http://portal.bsu.edu.ph:8083/index.php/BRJ/article/view/354
A22: 20 | B22: Jan-June 2023 | C22: CTE | D22: Direct or Inquiry? Science Teaching Orientations of Prospective Secondary Science Teachers | E22: Apler J. Bansiong | F22: Journal | G22: Mountain Journal of Science and Interdisciplinary Research 83 No. 1 | H22: Scopus | I22: Science teaching orientation, Epistemic modes, Inquiry instruction, Direct teaching, Didactic direct, Guided inquiry, Open Inquiry | J22: http://portal.bsu.edu.ph:8083/index.php/BRJ/article/view/355
A23: 22 | B23: Jan-June 2023 | C23: Outside Contributor | D23: Technology Leadership and Technology Integration in Selected Science High Schools in the National Capital Region: Basis for a Proposed Online Training Module | E23: Rafael V. Panganiban | F23: Journal | G23: Mountain Journal of Science and Interdisciplinary Research 83 No. 1 | H23: Scopus | I23: Education 4.0, International Technology Standards, Online Training, Technology Integration, Technology Leadership
A24: 21 | B24: Jan-June 2023 | C24: CSS | D24: Flexible Learning Opportunities and Challenges: Exploring the Experiences of Benguet State University During the COVID-19 Pandemic | E24: Ma. Theresa B. Dolipas, Karryl Mae C. Ngina, and Gigy G. Banes | F24: Journal | G24: Mountain Journal of Science and Interdisciplinary Research 83 No. 1 | H24: Scopus | I24: flexible learning, flexible learning challenges, flexible learning coping mechanisms, flexible learning opportunities | J24: http://portal.bsu.edu.ph:8083/index.php/BRJ/article/view/357
A25: 22 | B25: Jan-June 2023 | C25: NPRCRTC | D25: Documentation and Promotion of Using Minisett Technique in Seed Yam Production | E25: Dalen T. Meldoz, Violeta B. Salda, and Grace S. Backian | F25: Journal | G25: Mountain Journal of Science and Interdisciplinary Research 83 No. 1 | H25: Scopus | I25: yam minisett technique, seed yam, productivity, documentation | J25: http://portal.bsu.edu.ph:8083/index.php/BRJ/article/view/358
A26: 25 | B26: Jan-June 2023 | C26: Outside Contributor | D26: Market Chain Analysis of White Corn in Abra | E26: Jovinia S. Lucas | F26: Journal | G26: Mountain Journal of Science and Interdisciplinary Research 83 No. 1 | H26: Scopus | I26: market chain analysis, market chain, white corn, Abra
A27: 23 | B27: Jan-June 2023 | C27: CAH | D27: Strategic Competences of Local Tourist Guides | E27: Richard A. Giye and Jhordan T. Cuilan | F27: Journal | G27: Mountain Journal of Science and Interdisciplinary Research 83 No. 1 | H27: Scopus | I27: Strategic, Tour guides, Communication breakdown | J27: http://portal.bsu.edu.ph:8083/index.php/BRJ/article/view/360
A28: 24 | B28: Jan-June 2023 | C28: CSS | D28: Parenting Too Soon: Education and Child Care Concerns of College Student Mothers in the Cordillera Administrative Region | E28: Ann Heather B. Kiwang, Mursha D. Gapasin, and Gigy G. Banes | F28: Journal | G28: Mountain Journal of Science and Interdisciplinary Research 83 No. 1 | H28: Scopus | I28: Teenage pregnancy, Student mothers, Child care | J28: http://portal.bsu.edu.ph:8083/index.php/BRJ/article/view/361
A29: 25 | B29: Jan-June 2023 | C29: BSU Buguias | D29: Working Relationship Practices Between Administrators and Teachers: Effects on Teachers’ Job Performance | E29: Neivalyn B. Labenio | F29: Journal | G29: Mountain Journal of Science and Interdisciplinary Research 83 No. 1 | H29: Scopus | I29: Administrators, Teachers, Working relationship practices, Job performance | J29: http://portal.bsu.edu.ph:8083/index.php/BRJ/article/view/362
A30: 26 | B30: July - Dec 2023 | C30: CF | D30: Biodiversity Conservation in Mining Landscapes: a Systematic Review of Assessment Approaches in the Philippines | E30: Bernard Peter O. Daipan, Crusty E. Tinio, Nelson M. Pampolina | F30: Journal | G30: Philippine Journal of Science | H30: SCOPUS | I30: biodiversity, conservation, mining area, mineral production sharing agreement | J30: https://doi.org/10.56899/152.04.15
A31: 27 | B31: July - Dec 2023 | C31: CF | D31: Mapping Forest Vulnerability to Fire and Landslides in the Cordillera Region, Philippines | E31: Bernard Peter O. Daipan, Diomedes A. Racelis | F31: Journal | G31: Science and Engineering Journal (SCIENGGJ) | H31: SCOPUS/ Clarivate/ Web of Science (ISI) | I31: Cordillera, Forest Fire, GIS, Landslide, Vulnerability | J31: https://scienggj.org/2023-265/
A32: 28 | B32: July - Dec 2023 | C32: CIS | D32: Opportunities and limitations to social learning for sustainability: empirical insights from a participatory approach to community-based resource management in the Philippines | E32: Doreen Ingosan Allasiw,Toshinori Tanaka,Shogo Kudo &Takashi Mino | F32: Journal | G32: International Journal of Agricultural Sustainability | H32: SCOPUS/Clarivate/Web of Science (ISI) | I32: Participatory Approach; Social Learning; Sustainability; Community-based Irrigation Management; Institutions; Collective Action; Conflict Resolution | J32: https://doi.org/10.1080/14735903.2023.2239075
A33: 29 | B33: July - Dec 2023 | C33: CNS | D33: Plant species and ecosystem diversity along national road in mountain sites: The case of Kennon Road in Cordillera Central Range, Philippines | E33: Jones T. Napaldet | F33: Journal | G33: Taiwania | H33: SCOPUS/ Clarivate/ Web of Science (ISI) | I33: Conservation-important species, Kennon Road, Neotropical element, road biodiversity, Shannon diversity | J33: https://www.researchgate.net/profile/Jones-Napaldet/publication/373556574_Plant_species_and_ecosystem_diversity_along_national_road_in_mountain_sites_The_case_of_Kennon_Road_in_Cordillera_Central_Range_Philippines/links/64f1b91bc40f1d22df82ef02/Plant-species-and-ecosystem-diversity-along-national-road-in-mountain-sites-The-case-of-Kennon-Road-in-Cordillera-Central-Range-Philippines.pdf
A34: 30 | B34: July - Dec 2023 | C34: ULIS | D34: Gender Inclusivity of Library and Information Services | E34: Daniel S. Balbin, Jr. | F34: Journal | G34: PAARL Research Journal PRJ 2023; Vol. 9: 84-110 | H34: open access peer-reviewed | I34: Library services, library inclusivity, gender inclusivity, Library Bill of Rights, LGBTQIA+ | J34: https://www.ejournals.ph/article.php?id=20041
A35: 31 | B35: July - Dec 2023 | C35: ULIS | D35: Virtual Internship Experiences of Library and Information Science Students During the Pandemic | E35: Daniel Jr. Soriano Balbin, Russell Battad Dolendo | F35: Journal | G35: Journal of Information Science Theory and Practice | H35: Scopus | I35: library schools, in-service training, library science, models, educational | J35: https://doi.org/10.1633/JISTaP.2023.11.3.5
A36: 32 | B36: July - Dec 2023 | C36: CAH | D36: EXAMINING THE IMPACT OF SINGLE PARENTING ON THE ACADEMIC PERFORMANCE OF JUNIOR HIGH SCHOOL STUDENTS | E36: Aubrae Frances Engngeg Bannawi, Novia Praise Dewanan Foy-awen, Amir Sam Tagtag Joseph, Glayrheal Ducas Del Rosario, Lester Lyle Dayasen Andawi, Nover Luke Dalog Eslao, Ashlyn Jace Lagasca Banih, John Rey Osben Pelila | F36: Journal | G36: INTERNATIONAL JOURNAL OF EDUCATION, PSYCHOLOGY AND COUNSELLING | H36: open access peer-reviewed | I36: Single Parenting, Academic Performance, Junior High School Students, Correlational Study | J36: https://www.researchgate.net/profile/John-Rey-Pelila/publication/374006074_Examining_the_Impact_of_Single_Parenting_on_the_Academic_Performance_of_Junior_High_School_Students/links/65096d3382f01628f0310534/Examining-the-Impact-of-Single-Parenting-on-the-Academic-Performance-of-Junior-High-School-Students.pdf
A37: 33 | B37: July - Dec 2023 | C37: CF | D37: Phylogenetic relationships and historical biogeography of Otus species based on mitochondrial cytochrome b gene sequence | E37: Bernard Peter O. Daipan, Ivy Amor F. Lambio, Juan Carlos T. Gonzales, Nelson M. Pampolina | F37: Journal | G37: Israel Journal of Ecology and Evolution | H37: SCOPUS/ Clarivet / Web of Science (ISI) | I37: Bayesian; biogeography; Maximum Likelihood; Maximum Parsimony; Otus; phylogeny | J37: https://doi.org/10.1163/22244662-bja10062
A38: 34 | B38: July - Dec 2023 | C38: CHK | D38: Motivation and Effects of Adventure Sports Tourism in the Cordillera Administrative Region, Philippines | E38: Harland Gary B. Pawid | F38: Journal | G38: CONNEXION Journal of Humanities and Social Sciences, 12(2), | H38: open access peer-reviewed | I38: Adventure Sports Tourism, Environmental Awareness, Nature, Culture, Sustainable Tourism Development | J38: https://so05.tci-thaijo.org/index.php/MFUconnexion/article/view/266494/180114
... A45: 40 | B45: July - Dec 2023 | C45: CNS | D45: Morpho-Anatomy and Mathematical Modelling in Lilium philippinense Baker from Cordillera Central Range, Philippines | E45: Jennifer C. Paltiyan-Bugtong, Rey G. Lumpio, Jones T. Napaldet, | F45: Journal | G45: Trop Life Sci Res. 2023 Sep; 34(3): 217–235 | H45: Scopus from 2009 to 2023/ Clarivate (Emerging Sources Citation Index) | I45: Monocot Plant with Dicot Characters, Lilium philippinense, Lilium formosanum, Correlation, Regression | J45: https://doi.org/10.21315%2Ftlsr2023.34.3.12
A46: 41 | B46: July - Dec 2023 | C46: CF/GIS | D46: Land Use and Land Cover (LULC) Assessment within the Batanes Protected Landscapes and Seascapes. | E46: Doyog, Nova D.; Lumbres, Roscinto Ian C.; Talkasen, Lynn J.; Soriano, Deign Frolley C. | F46: Journal | G46: Philippine Journal of Science, 2023, Vol 152, Issue 5, p1753 | H46: Web of Science - Zoological Records; Scopus from 2009 to 2024 | J46: https://www.researchgate.net/profile/Roscinto-Ian-Lumbres/publication/374343068_Land_Use_and_Land_Cover_LULC_Assessment_within_the_Batanes_Protected_Landscapes_and_Seascapes/links/654f3d2ace88b87031de9040/Land-Use-and-Land-Cover-LULC-Assessment-within-the-Batanes-Protected-Landscapes-and-Seascapes.pdf
A47: 42 | B47: July - Dec 2023 | C47: CN | D47: Research Knowledge Transfer in the Nursing Education Colleges of two Selected State Universities in Luzon (Philippines) | E47: Brian Saludes Bantugan, Jonalyn Esco, Chevelle ValencianoGaan, and Denice Mikaela Navarro | F47: Journal | G47: International Journal of Arts and Social Science Volume 6 Issue 3, | H47: open access peer-reviewed | I47: Research, Research Knowledge, Knowledge Transfer, State Universities and Colleges, Nursing Education Research | J47: https://www.researchgate.net/profile/Brian-Bantugan/publication/369289239_Research_Knowledge_Transfer_in_the_Nursing_Education_Colleges_of_two_Selected_State_Universities_in_Luzon_Philippines/links/6413242392cfd54f84061ac7/Research-Knowledge-Transfer-in-the-Nursing-Education-Colleges-of-two-Selected-State-Universities-in-Luzon-Philippines.pdf
A48: 43 | B48: July - Dec 2023 | C48: CF | D48: Urban Forest Cover and LST Change Monitoring Through Optical and Thermal Remote Sensing Approach | E48: Nova D. Doyog | F48: Journal | G48: Journal of the Indian Society of Remote Sensing Volume 51, pages 2467–2480 | H48: Clarivate (Science Citation Index Expanded)/Scopus from 1973 to Present | I48: Image enhancement, Optical and thermal multi-temporal data, Urban forest degradation, Urban temperature | J48: https://link.springer.com/article/10.1007/s12524-023-01779-w
A49: 44 | B49: July - Dec 2023 | C49: CSS/CNS/OSS | D49: Psychological Vulnerabilities and Mental Health Measures | E49: Karryl Mae C. Ngina, Liza A. Ngiao, Joel V. Lubrica, and Editha A. Grande | F49: Journal | G49: Mountain Journal of Science and Interdisciplinary Research 83 No. 2 | H49: Scopus | I49: Mental Health, Depression, Anxiety, Stress, Self-Harm, Life Skills, Social Support, Psychological Vulnerabilities,Protective Factors | J49: http://portal.bsu.edu.ph:8083/index.php/BRJ/article/view/382/411
A50: 45 | B50: July - Dec 2023 | C50: CSS/NPRCRTC/HORTI | D50: Scaling Up Rootcrops Technology and the Women's Wisdom in the Conservation of Sweetpotato Varieties | E50: Ruth S. Batani, Kacy O. Labon, Teresita D. Masangcay, and Rhea S. Loncio | F50: Journal | G50: Mountain Journal of Science and Interdisciplinary Research 83 No. 2 | H50: Scopus | I50: Sweetpotato, Fusarium Wilt, Trichoderma,Tissue Culture Technology, Seed Exchange, Women's Conservation | J50: http://portal.bsu.edu.ph:8083/index.php/BRJ/article/view/376/405
A51: 46 | B51: July - Dec 2023 | C51: IHFSA/CA | D51: Effective Density of Lure Trap Against Coffee Berry Borer Infesting Arabica Coffee (Coffea arabica Linn.) in Benguet, Philippines | E51: Gemma S. Das-ilen, Hazzel Kith B. Dumpayan, and Bonie S. Ligat | F51: Journal | G51: Mountain Journal of Science and Interdisciplinary Research 83 No. 2 | H51: Scopus | I51: Coffee Berry Borer, Lure Traps,Arabica Coffee | J51: http://portal.bsu.edu.ph:8083/index.php/BRJ/article/view/377/406
A52: 47 | B52: July - Dec 2023 | C52: HORTI/CA | D52: Direct Organogenesis and Regeneration of Arabica Coffee Cultivars | E52: Milagros R. Dumaslan, Belinda A. Tad-awan, and Sheryl B. Manuel | F52: Journal | G52: Mountain Journal of Science and Interdisciplinary Research 83 No. 2 | H52: Scopus | I52: Coffea arabica,Direct Organogenesis,Sub-culture,Acclimatization | J52: http://portal.bsu.edu.ph:8083/index.php/BRJ/article/view/378/407
A53: 52
A54: 53
A55: 54 | C55: Prepared by: | D55: NOEL A. LENGUAJE | E55: Noted by: CHERYLL C. LAUNIO
A56: 55 | D56: REPO Staff | E56: REPO Director

Sheet Data_2022
A1: No. | B1: Year | C1: College/Institute | D1: Title | E1: Author(s) | F1: Pub Type | G1: Journal/Book | H1: Category | I1: Keywords | J1: URL | K1: Citations | L1: Remarks
A2: 1 | B2: 2022 (Jan-June) | C2: CF | D2: Domestication of “Deguai” (Saurauia bontocensis Merr.) at La Trinidad, Benguet, Philippines | E2: John G. Tacloy, Conrado C. Bao-idang, Sano L. Ngiwas, Marjie B. Esteban, and Milbrenne D. Yabes | F2: Journal | I2: “deguai,” rooting hormones, Saurauia bontocensis Merr., stem cuttings, tree domestication, wild fruit trees | J2: https://philjournalsci.dost.gov.ph/images/pdf/pjs_pdf/vol151no1/domestication_of_denguai_at_La_Trinidad_Benguet_.pdf
A3: 2 | B3: 2022 (Jan-June) | C3: CAH | D3: Philosophy of education in a new key: A collective writing project on the state of Filipino philosophy of education | E3: Gina A. Opiniano, Liz Jackson, Franz Giuseppe F. Cortez, Elizer Jay de los Reyes, Marella Ada V. Mancenido-Bolaños, Fleurdeliz R. Altez-Albela, Rodrigo Abenes, Jennifer Monje,Tyrene Joy B. Basal, Peter Paul E. Elicor, Ruby S. Suazo & Rowena Azada-Palacios | F3: Discussion | J3: https://www.tandfonline.com/doi/full/10.1080/00131857.2021.2008357?src= | L3: Co-author (Is this kind of format considered for Humanities type of paper publication?)
A4: 2 | B4: 2022 (Jan-June) | C4: CNAS | D4: Assessment of the University Vision, Goals, Mission and Program Objectives: A Management Protocol for Quality Assurance | E4: Bretel B. Dolipas*, Julie A. Buasen, Maria Azucena B. Lubrica, Phil S. Ocampo, Kenneth B. Pakipac, Marycel T. Sajise & Precious M. Valentin | F4: Journal | I4: university vision, mission, goals, objectives, awareness, personnel | J4: https://www.athensjournals.gr/business/2022-8-2-3-Dolipas.pdf
A5: 3 | B5: 2022 (Jan-June) | C5: CEAT | D5: Assessment of Quality Indicators of Pressed Biofuel Produced from Coarse Herbaceous Plants and Determination of the Influence of Moisture on the Properties of Pellets | E5: Algirdas Jasinskas*, Vytautas Kleiza ,Dionizas Streikus, Rolandas Domeika, Edvardas Vaiciukevičius, Gvidas Gramauskas and Marvin T. Valentin | F5: Journal | I5: coarse stem plants; solid biofuel; milling; granulation; quality indicators; burning; emissions; energy evaluation | J5: https://www.mdpi.com/2071-1050/14/3/1068 | L5: Co-author
A6: 4 | B6: 2022 (Jan-June) | C6: CNS | D6: Ecosystem services through the lens of indigenous people in the highlands of Cordillera Region, Northern Philippines | E6: Joyce N. Paing, Lenny G. J. van Bussel, Romeo A. Gomez, Jr., Lars G. Hein | F6: Journal | I6: Local community, Ecosystem services, Human well-being, Ethnicity, Cordillera region, Philippines | J6: https://www.sciencedirect.com/science/article/pii/S0301479722001700
A7: 5 | B7: 2022 (Jan-June) | C7: CF | D7: Root growth potential and seedling growth of kamagong (Diospyros blancoi A. DC.) influenced by root pruning | E7: Milbrenne D. Yabes, Gerryc P. Alfonso, and Vida Q. Carandang | F7: Journal | I7: Kamagong; Diospyrus blancoi; root pruning; root growth potential; seedling quality | J7: https://brill.com/view/journals/ijee/aop/article-10.1163-22244662-bja10034/article-10.1163-22244662-bja10034.xml | L7: Co-author
A8: 6 | B8: 2022 (Jan-June) | C8: ULIS | D8: Veterinary Medicine Students' Use of Library Resources and Access to Scientific Papers | E8: Noel W. Cabfilan | F8: Journal | I8: Veterinary Medicine Library, Library usage, Reading scientific papers, Library resources | J8: https://digitalcommons.unl.edu/libphilprac/6889
A9: 7 | B9: 2022 (Jan-June) | C9: BSU-Bokod | D9: Characterizing the Ideal Audio-Visual Learning Content of Writing Course Learned in Distance | E9: Chester Esnara et al. | F9: Journal | I9: audiovisual aids, COVID-19 pandemics, learning process, and learning strategy | J9: https://doi.org/10.21512/lc.v16i1.7731 | L9: Co-Author
A10: 8 | B10: 2022 (Jan-June) | C10: College of Engineering | D10: Small-scale Demucilager Machine for Arabica Coffee (Coffea arabica) | E10: Erickson N. Dominguez and Jeffrey A. Lavarias | F10: Journal | I10: Coffee demucilager; mechanical mucilage removal; coffee mucilage; natural fermentation | J10: https://www.researchgate.net/profile/Jeffrey-Lavarias/publication/360471633_Small-scale_Demucilager_Machine_for_Arabica_Coffee_Coffea_arabica/links/6283301b37d496476ab57a79/Small-scale-Demucilager-Machine-for-Arabica-Coffee-Coffea-arabica.pdf | L10: Co-Author
A11: 9 | B11: 2022 (Jan-June) | C11: CIS | D11: Mental Toughness and Character Building through Sports | E11: Jumel C. Miller, Russell B. Dolendo | F11: Journal | I11: Mental Toughness, Character Building, Sports | J11: https://www.journalppw.com/index.php/jpsp/article/view/3841/2513 | L11: Co-Author
A12: 11 | B12: 2022 (Jan-June) | C12: CA, CF | D12: Climate-Resilient Agriculture Assessment, Targeting and Prioritization for the Adaptation, and Mitigation Initiative in Agriculture (AMIA) in the Cordillera Administrative Region, Philippines | E12: Elizabeth E. Supangco, Janet P. Pablo, Roscinto Ian C. Lumbres, Charis Mae Tolentino-Neric, Levi Ezekiel O. Daipan, Gillian Katherine Inciong & Ralphael Gonzales | F12: Book | I12: Adaptation, Climate Resilient Agri-fisheries, Climate Risk Vulnerability Assessment, Mitigation | J12: https://link.springer.com/chapter/10.1007/978-981-19-0213-0_11 | L12: Co-Author
A13: 10 | B13: 2022 (Jan-June) | C13: CNAS | D13: Boesenbergia igorota (Zingiberaceae), a new species from the Cordillera Central Range, Northern Philippines | E13: Rene Vincent B. Tad-o, Joanna I. Alafag, Jones T. Napaldet | F13: Journal | I13: Boesenbergia alba, Cordillera Central Range, critically endangered, Igorot women, morphometrics, flora | J13: https://www.researchgate.net/publication/360886693_Boesenbergia_igorota_Zingiberaceae_a_new_species_from_the_Cordillera_Central_Range_Northern_Philippines | L13: Co-Author
A14: 11 | B14: 2022 (Jan-June) | C14: CHET | D14: Time-honored praxis in preparing smoked meat delicacy (kinuday) of the ibaloy indigenous people in Benguet, Philippines | E14: Cynthia D. Garambas, Myrna Benita Z. Luna & Consuelo T. Chua | F14: Journal | I14: Ibaloy indigenous group, Traditional smoked pork delicacy (kinuday), Indigenous knowledge on meat smoking, Benguet, Philippines | J14: https://journalofethnicfoods.biomedcentral.com/articles/10.1186/s42779-022-00135-6 | L14: Co-Author
A15: 12 | B15: 2022 (Jan-June) | C15: Humanities Department, Benguet State University | D15: Albubo Festival as a Tool to Enhance Community Engagement of Buguias, Benguet Residents | E15: Jenalyn P. Oligo, Jaicelle P. Smith, Joseph B. Quinto | F15: Journal | I15: Albubo festival, Buguias residents, community engagement, cultural festival, enhance effective | J15: https://media.neliti.com/media/publications/410862-albubo-festival-as-a-tool-to-enhance-com-35c084dd.pdf
A16: 15 | B16: 2022 (Jan-June) | C16: CA, CNAS | D16: Native/Heirloom Rice in the Cordilleras: Status, Conservation, and Utilization | E16: Romeo Jr. A. Gomez, Belinda A. Tad-awan, Alexander W. Fagyan, Joyce N. Paing & Esther Josephine D. Sagalla | F16: Book | I16: Native, Heirloom rice, Cordillera, Status, Conservation, Utilization | J16: https://link.springer.com/chapter/10.1007/978-981-16-7699-4_6
A17: 13 | B17: 2022 (Jan-June) | C17: BSU-Bokod | D17: Revisiting Philippine Folklore: Ba-diw as Discourse of Ethnicity in the Nonfolklorist Humanistic Lens | E17: Chester B. Esnara | F17: Journal | I17: Discourse of ethnicity, Ethnolinguistic literary critique, Ibaloy Ba-diw, Discourse analysis, Humanistic nonfolklorist lens | J17: https://www.al-kindipublisher.com/index.php/ijllt/article/view/3662
A18: 14 | B18: 2022 (Jan-June) | C18: BSU-Buguias | D18: Benguet State University-Buguias Campus in 17 Years (1998-2015): Graduate Employability and Student Satisfaction | E18: Jayne B. Miranda, Martha C. Lagadan, Rio Ann B. Arceo, Samuel P. Reyes, and Julius B. Dominguez | F18: Journal | I18: BSU-Buguias Campus, Graduate Employability, Tracer Study, Employer Satisfaction, Student Satisfaction | J18: http://journals.bsu.edu.ph/index.php/BRJ/issue/view/37
A19: 15 | B19: 2022 (Jan-June) | C19: BSU-Buguias | D19: Ang Paggamit ng Wikang Filipino sa Pagtuturo sa Larang ng Agrikultura | E19: Divinia K. Dominguez | F19: Journal | I19: wikang Filipino, larang ng agrikultura, wikang panturo | J19: http://journals.bsu.edu.ph/index.php/BRJ/issue/view/37
A20: 19 | B20: 2022 (Jan-June) | C20: Outside Contributor (Philippine Normal University) | D20: Effectiveness of K to 12 DepEd-Provided and Teacher-Made Modules on Student Performance in Technology and Livelihood Education Exploratory Subject Areas | E20: Lorena A. Castro | F20: Journal | I20: K to 12 curriculum, Technology and Livelihood Education, module effectiveness | J20: http://journals.bsu.edu.ph/index.php/BRJ/issue/view/37
A21: 16 | B21: 2022 (Jan-June) | C21: BSU-CTE | D21: Professional Development and Competence of School Heads in Urban and Rural Areas Leadership | E21: Soraya T. Faculo and Divina M. Yango | F21: Journal | I21: School leadership, Instructional leadership, Student-centered learning | J21: http://journals.bsu.edu.ph/index.php/BRJ/issue/view/37 | L21: Co-author
A22: 17 | B22: 2022 (Jan-June) | C22: BSU-Buguias | D22: Development and Evaluation of Task-Based Material in Business Mathematics for Senior High School | E22: Jayne B. Miranda and Elsie M. Pacho | F22: Journal | I22: Task-based Material, Readability, Business Mathematics | J22: http://journals.bsu.edu.ph/index.php/BRJ/issue/view/37
A23: 18 | B23: 2022 (Jan-June) | C23: BSU-Buguias | D23: Utilization of Rice Hull Char-Based Compost for Potato (Solanum tuberosum) Production | E23: Bennylyn B. Puyongan | F23: Journal | I23: Rice Hull Char-Based Compost (RHCBC), Potato, Rice hull | J23: http://journals.bsu.edu.ph/index.php/BRJ/issue/view/37
A24: 23 | B24: 2022 (Jan-June) | C24: Outside Contributor (Visayas State University) | D24: Ratooning Response of Lowland Rice NSIC Rc216 to the Residual Effect of Goat Manure Application | E24: Alexis Gonzales and Dionesio M. Bañoc | F24: Jounal | I24: Fertilizer, gross margin, ratoon, residual effect, stubble | J24: http://journals.bsu.edu.ph/index.php/BRJ/issue/view/37
A25: 19 | B25: 2022 (Jan-June) | C25: BSU-CA | D25: Isolation, Characterization, Identification, and Preliminary Pathogenicity Test of Entomopathogenic Fungi Against Whitefly (Bemesia tabaci) | E25: Rechelle B. Peningeo, Judith G. Lawilao, and Asuncion L. Nagpala | F25: Journal | I25: Entomopathogenic Fungi (EPF), A. placenta, A. goldiana, H. epiphylla, Whitefly | J25: http://journals.bsu.edu.ph/index.php/BRJ/issue/view/37
A26: 20 | B26: 2022 (Jan-June) | C26: BSU-Buguias | D26: Operations and Key Competencies of Micro-Scale Sewing Enterprises in Baguio City and La Trinidad, Benguet | E26: Susan D. Ansibey | F26: Journal | I26: Competency, Micro-scale, Sewing enterprise | J26: http://journals.bsu.edu.ph/index.php/BRJ/issue/view/37
A27: 21 | B27: 2022 (Jan-June) | C27: BSU-CHK/UHS | D27: Morphological Fitness Profile and the Prevalence of Hypertension and Diabetes Among Benguet State University Employees | E27: Eduardo P. Laconsay and Florence V. Poltic | F27: Journal | I27: anthropometric measurement, BMI, body fat percentage, cardiovascular disease risk factor, waist circumference, morphological fitness, obesity, overweight | J27: http://journals.bsu.edu.ph/index.php/BRJ/issue/view/37
A28: 27 | B28: 2022 (Jan-June) | C28: Outside Contributor (Tarlac State University) | D28: Citizen’s Satisfaction with Local Government Response in a Selected Municipality of Tarlac | E28: Patricia Ann D. Estrada and Izelle C. Francisco | F28: Journal | I28: Citizen Satisfaction, Local Goverment Response, Citizen Awareness, Availment, Satisfaction | J28: http://journals.bsu.edu.ph/index.php/BRJ/issue/view/37
A29: 22 | B29: 2022 (Jan-June) | C29: ISRD | D29: Farmer-led Small-scale Irrigation Systems Management in Highland Vegetable Farming in the Cordillera Region, Philippines | E29: Cheryll C. Launio & Marivic Abyado | F29: Journal | J29: https://jemad.cem.uplb.edu.ph/issues/jemad-vol-8-no-1/
A30: 23 | B30: 2022 (Jan-June) | C30: CNAS | D30: Example–conclusion map in teaching simple interest: A lesson study | E30: Fleur De Cory Apasen Ngiwas, Daisy Lyn F. Mariano, Jayson G. Barsana, Michelle P. Cruz, Levi Elipane | F30: Journal | I30: Critical pedagogy Example-conclusion map Lesson study Problem solving maps Simple interest | J30: https://files.eric.ed.gov/fulltext/EJ1341213.pdf | L30: Co-author
A31: 24 | B31: 2022 (Jan-June) | C31: CF | D31: Comparative analysis of the leaf architectural characters of Saurauia bontocensis Merr. and Saurauia polysperma (Blanco) Merr. with the application of Digital Image Analysis Software | E31: Bernard Peter O. Daipan, Inocencio E. Buot, Jr. | F31: Journal | I31: Digital Image Analysis, leaf architecture, plant taxonomy, Saurauia bontocensis, Saurauia polysperma | J31: https://smujo.id/biodiv/article/view/11265
A32: 25 | B32: 2022 (Jan-June) | C32: CNS | D32: Toxicity and Antioxidant Properties of Pacific Rain Tree (Samanea saman (Jacq.) Merr.) Pods | E32: James Kennard S. Jacob; Jennifer C. Paltiyan; Hezekiah Mirielle P. Aguinaldo; Ron Patrick Cuagdan Campos | F32: Journal | I32: Rain tree, antioxidant, cytotoxicity, embryotoxicity, Samanea saman | J32: https://www.jabsonline.org/index.php/jabs/article/view/897 | L32: Co- author
A33: 26 | B33: 2022 (July-Dec.) | C33: CNAS | D33: Liquid Crystal Display (LCD) based Instruction and Physics Performance | E33: Bretel B. Dolipas*, Freda Kate D. Samuel± & Kenneth B. Pakipac• | F33: Journal | I33: LCD, physics performance, sex, PowerPoint presentation, physics concept, problem solving | J33: https://www.athensjournals.gr/sciences/2022-9-3-4-Dolipas.pdf
A34: 27 | B34: 2022 (July-Dec.) | C34: CHET | D34: Organoleptic and Physicochemical Characterization of Ethnic Smoked Pork Delicacy (Kinuday) Produced by the Ibaloy Indigenous People in Cordillera, Philippines | E34: Cynthia D. Garambas, Myrna Benita Z. Luna, and Consuelo T. Chua | F34: Journal | I34: Ibaloy indigenous group in Benguet, organoleptic characterization, Philippines, traditional smoked pork delicacy (kinuday) | J34: https://philjournalsci.dost.gov.ph/images/pdf/pjs_pdf/vol151no4/organoleptic_and_physicochemical_characterization_of_ethnic_smoked_pork_delicacy_kinuday_.pdf | L34: Author
A35: 28 | B35: 2022 (July-Dec.) | C35: CAH | D35: Language Theses and Dissertation Landscapes: An Analysis of Research Analyses | E35: Fermilyn D Adais, Kara S. Panolong | F35: Journal | I35: Content Analysis, Systematic Review, Language Research, Theses, Dissertations, Research Features | J35: http://www.cjess.ca/index.php/home/article/view/48 | L35: Co-author
A36: 29 | B36: 2022 (July-Dec.) | C36: Buguias | D36: Stress and Coping Strategies of University Employees in Buguias, Benguet | E36: Elizabeth M. Bay-an*, Gracita N. Estocapio, and Melody C. Domalti | F36: Journal | I36: BSU-Buguias Campus, Coping Strategies, Stress, Stressors | J36: http://portal.bsu.edu.ph:8083/index.php/BRJ/article/view/329
A37: 30 | B37: 2022 (July-Dec.) | C37: Buguias | D37: Civil Engineering Students’ Problem-Solving Skills on Calculus-Based Problems | E37: Nelson S. Banos | F37: Journal | I37: Problem-solving, Engineering Solving Skills, Rates Problems, Calculus Problems | J37: http://portal.bsu.edu.ph:8083/index.php/BRJ/article/view/334
A38: 31 | B38: 2022 (July-Dec.) | C38: CA | D38: Diversity of Ricebean (Vigna umbelleta L.) Germplasm in the Northern Philippine Highlands Based on Agro-morphological Characteristics and Simple Sequence Repeat Markers | E38: Belinda A. Tad-awan* and Hilda V. Palaes | F38: Journal | I38: agro-morphological characters, genetic diversity, genetic similarities, ricebean germplasm, simple sequence repeats | J38: http://portal.bsu.edu.ph:8083/index.php/BRJ/article/view/337
A39: 32 | B39: 2022 (July-Dec.) | C39: CIS | D39: Upscaling Organic Agriculture System of La Trinidad, Benguet Farmers | E39: Christine Grace S. Fuchigami, and Faith N. Belingon | F39: Journal | I39: Benguet agriculture, Benguet women, Good farming practices, Good marketing practices, Gender in farming, Women in agriculture | J39: http://portal.bsu.edu.ph:8083/index.php/BRJ/article/view/332
A40: 33 | B40: 2022 (July-Dec.) | C40: CTE | D40: Pre-Service Teachers' Technology Literacy Skills for Blended Learning: Case fo Four Universities in Baguio City and Benguet, Philippines | E40: Almon B. Bokilis | F40: Journal | I40: Blended Learning, Technology Literacy, Knowledge Deepening | J40: http://portal.bsu.edu.ph:8083/index.php/BRJ/article/view/335
A41: 34 | B41: 2022 (July-Dec.) | C41: NPRCRTC | D41: Lesser Yam (Dioscorea esculenta) Grown and Knowledge Transfer Among Indigenous People in Northern Philippines | E41: Grace S. Backian, Betty T. Gayao, and Dalen T. Meldoz | F41: Journal | I41: lesser yam, traditional knowledge, Northern Luzon IPs, tugui, Dioscorea esculenta | J41: http://portal.bsu.edu.ph:8083/index.php/BRJ/article/view/330
A42: 35 | B42: 2022 (July-Dec.) | C42: ISRD | D42: BSU Time Use: Engaging Faculty Researchers Before and After the Disallowance Disaster | E42: Ruth S. Batani and Kacy O. Labon | F42: Journal | I42: Time Use, Faculty Researchers, Incentives | J42: http://portal.bsu.edu.ph:8083/index.php/BRJ/article/view/331
A43: 36 | B43: 2022 (July-Dec.) | C43: IHFSA/CA | D43: Effects of Roast Levels on the Physical Properties, Microbial Contaminants, and Cup Quality of Arabica Coffee | E43: Andres A. Basalong*, Von Y. Amado, and Hazen Lyn B. Talbino | F43: Journal | I43: Arabica coffee, roast levels, cup quality | J43: http://portal.bsu.edu.ph:8083/index.php/BRJ/article/view/338
A44: 43 | B44: 2022 (July-Dec.) | C44: Outside Contributor | D44: Motivated Strategies for Learning and Online Learning Readiness of Students in Maritime Institution in Central Luzon, Philippines | E44: Froilan D. Mobo | F44: Journal | I44: Motivated strategies for learning, Online learning readiness, Maritime Institutions, Central Luzon | J44: http://portal.bsu.edu.ph:8083/index.php/BRJ/article/view/336
A45: 37 | B45: 2022 (July-Dec.) | C45: CSS | D45: Stress, Anxiety, Depression Levels and Coping Mechanisms of Students and Teachers: A School-based Population Survey | E45: Karryl Mae C. Ngina*, Ann Heather B. Kiwang, and Lance Angelo B. Layugan | F45: Journal | I45: Mental health, Stress, Anxiety, Depression | J45: http://portal.bsu.edu.ph:8083/index.php/BRJ/article/view/333
A46: 38 | B46: 2022 (July-Dec.) | C46: CNS | D46: THE PLANT DIVERSITY OF MT. ULAP ECO-TRAIL IN CORDILLERA CENTRAL RANGE, PHILIPPINES: AN INSIGHT ON THE EFFECT OF ECOTOURISM IN A SECONDARY FOREST | E46: Maricel A. Guron, Gideon Narvaez, Joanna I. Alafag and Jones T. Napaldet | F46: Journal | I46: diversity indices, ecotourism, endangered species, floral diversity, Mt. Ulap Eco-Trail, secondary forest | J46: https://www.muzeulbrailei.ro/uploads/img/stiintele-naturii/Volume%2012/02JWB2022122550.pdf
A47: 39 | B47: 2022 (July-Dec.) | C47: CF | D47: Evaluating the species distribution patterns of the genus Saurauia Willd. in the Philippines using geospatial analysis | E47: Bernard Peter O. Daipan, Inocencio E. Buot, Jr., Nelson M. Pampolina3 | F47: Journal | I47: Climate change, conservation, geographic information system, Saurauia, species distribution, systematics, taxonomy | J47: https://oaj.fupress.net/index.php/webbia/article/download/13193/11413
A48: 40 | B48: 2022 (July-Dec.) | C48: Bokod | D48: Translanguaging in the analysis of narrative techniques and discourse styles in selected Philippine short novels | E48: Chester B. Esnara | F48: Journal | I48: translanguaging, language-literature interface, narrative techniques, discourse styles, language and thought, modularity of the mind | J48: https://doi.org/10.58256/rjah.v3i4.960
A49: 41 | B49: 2022 (July-Dec.) | C49: CAH | D49: On Code-Switching in English Major Courses | E49: Joseph B. Quinto, and Aiza Bheal M. Kitani | F49: Journal | I49: code-switching, Bachelor of Secondary Education students majoring in English, English language professors, sequential explanatory mixed methods, higher education | J49: https://www.researchgate.net/profile/Aiza-Bheal-Kitani-2/publication/366578271_539_wwwwjournal-innovations/links/63a8391e03aad5368e3bafe7/539-wwwwjournal-innovations.pdf
A50: 42 | B50: 2022 (July-Dec.) | C50: CAH | D50: Seize the day or seize theses? The challenges in undergraduate thesis writing | E50: Joseph B. Quinto | F50: Journal | I50: no keywords | J50: http://www.iier.org.au/iier32/quinto.pdf
A51: 43 | B51: 2022 (July-Dec.) | C51: CAH | D51: CMO No. 15, S. 2019: Graduate Students, Are You Ready for This? | E51: Joseph B. Quinto | F51: Journal | I51: CHED Memo Order, research publication, mentorship | J51: https://philpapers.org/rec/QUICN
A52: 44 | B52: 2022 (July-Dec.) | C52: ULIS | D52: Assessment of Information Literacy and Fake News Identification of Benguet State University Freshmen: Implications for Library Literacy Program | E52: Daniel B. Balbin | F52: Journal | J52: https://www.researchgate.net/publication/365070610_Assessment_of_Information_Literacy_and_Fake_News_Identification_of_Benguet_State_University_Freshmen_Implications_for_Library_Literacy_Program
A53: 45 | B53: 2022 (July-Dec.) | C53: CNS | D53: Floral Diversity of Remnant Mossy Forest Patches in Atok, Benguet, Northern Philippines | E53: Jennifer C. Paltiyan-Bugtong, Cleefershel P. Kiligto, Shaira Shane D. Cajigan, Judy O. Agtarap and Jones T. Napaldet | F53: Journal | I53: baseline for conservation, Benguet, forest patches, mossy forest | J53: https://www.researchgate.net/publication/366983362_FLORAL_DIVERSITY_OF_THE_REMNANT_MOSSY_FOREST_PATCHES_IN_ATOK_BENGUET_NORTHERN_PHILIPPINES
A54: 46 | B54: 2022 (July-Dec.) | C54: CAH | D54: ISCORE Model: Formative feedback is core in synchronous classes | E54: Joseph B. Quinto | F54: Journal | I54: Formative Feedback; Synchronous Sessions; English Classes; Senior High School; Interpretive Phenomenology. | J54: https://www.researchgate.net/profile/Joseph-Quinto/publication/367654950_ISCORE_Model_Formative_feedback_is_core_in_synchronous_classes/links/63da19fc64fc8606380358ee/ISCORE-Model-Formative-feedback-is-core-in-synchronous-classes.pdf
A55: 47 | B55: 2022 (July-Dec.) | C55: BSU-Bokod | D55: The Consequences of Excessive Vegetable Production | E55: Heronima Sanchez | F55: Journal | I55: Amuyo, Agriculture, Barangay, Consequences, Vegetable Production | J55: https://journals.e-palli.com/home/index.php/ajmri/article/view/1035
A56: 48 | B56: 2022 (July-Dec.) | C56: CAH | D56: Pagkatuto ng mga Mag-aaral Na Kankanaey ng Wikang Filipino Bilang Pangalawang Wika | E56: Dominga S. Tomas, Joshua Payangdo, & Emmalyn Sagayo | F56: Journal | I56: Pagkatuto, Pangalawang Wika, Kankana-ey, Filipino | J56: https://www.ijams-bbp.net/archive/vol-2-issue-11-november/pagkatuto-ng-mga-mag-aaral-na-kankanaey-ng-wikang-filipino-bilang-pangalawang-wika/
A57: 56
A58: 57 | C58: Prepared by: | D58: NOEL A. LENGUAJE | E58: Noted by: CHERYLL C. LAUNIO
A59: 58 | D59: REPO Staff | E59: REPO Director
A60: 59
A61: 60
A62: 61
A63: 62
A64: 63
A65: Sustainable Development Goals (SDGs)
A66: SDG 1-No Poverty
A67: SDG 2-Zero Hunger
A68: SDG 3-Good Health and Well-being
A69: SDG 4-Quality Education
A70: SDG 5-Gender Equality
A71: SDG 6- Clean Water and Sanitation
A72: SDG 7- Affordable and Clean Energy
A73: SDG 8- Decent Work and Economic Growth
A74: SDG 9- Industry, Innovation and Infrastructure
A75: SDG 10- Reduced Inequalities
A76: SDG 11-Sustainable Cities and Communities
... A82: SDG 17-Partnership for the Goals

Sheet Data_2021
A1: No. | B1: Year | C1: College/Institute | D1: Title | E1: Author(s) | F1: Pub Type | G1: Journal/Book | H1: Category | I1: Keywords | J1: URL | K1: Citations | L1: Remarks
A2: 1 | B2: 2021 | C2: CF | D2: Diagnosing pristine pine forest development through pansharpened-surface-reflectance Landsat image derived aboveground biomass productivityForest Ecology and Management | E2: Nova D.Doyog, Chinsu Lin, Young Jin Lee, Roscinto Ian C.Lumbres, Bernard Peter O.Daipan, Derek C.Bayer, Christine P. Parian | F2: Journal | J2: https://www.sciencedirect.com/science/article/abs/pii/S0378112721001006?via%3Dihub
A3: 2 | B3: 2021 | C3: CF | D3: Detection of Forest Cover Disturbances Using Synthetic Aperture Radar (SAR) Time Series Data in the Mount Pulag National Park: A Key Biodiversity Area in Luzon, Philippines | E3: Bernard Peter O. Daipan | F3: Journal | J3: https://philjournalsci.dost.gov.ph/publication/special-issues/biodiversity/104-vol-150-s1/1359
A4: 3 | B4: 2021 | C4: ISRD | D4: "Concern for Community": Case of cooperatives in the Cordillera Region | E4: Cheryll C. Launio and Marycris Sotelo | F4: Journal | J4: https://www.sciencedirect.com/science/article/abs/pii/S2213297X21000021
A5: 4 | B5: 2021 | C5: CNS | D5: Ecological distribution and soil-vegetation analysis of the indigenous vegetable panawil (Leptosolena haenkei C. Presl.) in specific areas of Benguet and Mountain Province, Philippines | E5: Joyce N. Paing & Romeo A. Gomez Jr. | F5: Journal | J5: https://link.springer.com/article/10.1007/s42965-020-00131-4
A6: 5 | B6: 2021 | C6: CSS | D6: Should beach travel in the Philippines resume during the COVID-19 outbreak? | E6: G.A. Opiniano∗, H.T. Biana, C.M. Dagwasi, J.J.B. Joaquin | F6: Editorial Type | J6: https://www.ncbi.nlm.nih.gov/pmc/articles/PMC7572131/
A7: 6 | B7: 2021 | C7: CE | D7: Processing of Wild Sunflower with Different Moisture Contents into Solid Bio Fuel | E7: Dummapi, F. T., Liniasan, J. I., Valentin, M. T., Onalan, M. B., Dumalhin, L. D., Galad, M. N., Ciolkosz, D., Jasinskas, A., & Kelly, E. J. | F7: Journal | J7: https://journaljenrr.com/index.php/JENRR/article/view/30185
A8: 7 | B8: 2021 | C8: CE | D8: Concept Design of a Portable Carrot Seeder | E8: Marvin T. Valentin, Alex Smeets, Daniel E. Ciolkosz, Milagros B. Onalan, Alvin C. Dulay, Leonardo D. Dumalhin, Constantino T. Sudaypan Sr., Cheryll C. Launio, Marlon N. Galad, Roger Lee M. Suclad and Keithlern M. Pagnas | F8: Journal | J8: https://www.journaljerr.com/index.php/JERR/article/view/17302
A9: 8 | B9: 2021 | C9: CPAG | D9: The Perspective Of The Cordilleran People On The Political, Economic And Socio-Cultural Advantages Of Federalism | E9: Renebeth G. Donguiz | F9: Journal | J9: https://doi.org/10.17762/turcomat.v12i4.1388
A10: 9 | B10: 2021 | C10: BSU Bokod | D10: Assessing the Listening Proficiency of ESL Students in a Pandemic | E10: Chester B. Esnara | F10: Journal | J10: https://doi.org/10.32996/ijllt.2021.4.4.10
A11: 10 | B11: 2021 | C11: CPAG | D11: Interventions in Addressing Gender Issues in the Classroom | E11: Gretchen Gaye C. Ablaza | F11: Journal | J11: https://doi.org/10.17762/turcomat.v12i3.2162
A12: 11 | B12: 2021 | C12: CF | D12: Local knowledge and practices towards the ecological restoration of selected landscape in Atok, Benguet, Philippines | E12: Kenneth A. Laruan, Landicho LD, Ocampo MTNP, Cabahug RED, Abadillos MG, Cosico RSA, Castillo AKA, Ramirez MAJP | F12: Journal | J12: https://smujo.id/biodiv/article/view/8448
A13: 12 | B13: 2021 | C13: CF | D13: Monitoring of Land Use and Land Cover Changes in Mt. Pulag National Park Using Landsat and Sentinel Imageries | E13: Nova D. Doyog, Roscinto Ian C. Lumbres, and Zenaida G. Baoanan | F13: Journal | J13: https://philjournalsci.dost.gov.ph/images/pdf/pjs_pdf/vol150no4/monitoring_of_land_use_and_land_cover_changes_in_Mt_Pulag_.pdf
... A43: 42 | B43: 2021 | C43: CAH | D43: Katutubong Kaalaman: Pananaw at Integrasyon sa Akademikong Filipino | E43: Faustina T. Dio-as, Dominga S. Tomas | F43: Journal | J43: not included in the website of the journal
A44: 43
A45: 44
A46: 45 | C46: Prepared by: | D46: NOEL A. LENGUAJE | E46: Noted by: CHERYLL C. LAUNIO
A47: 46 | D47: REPO Staff | E47: REPO Director
A48: 47
A49: 48
A50: 49
A51: 50
A52: 51
A53: 52
A54: 53
A55: 54
A56: 55
A57: 56
A58: 57
A59: 58
... A67: 66

Sheet Data_2020
A1: No. | B1: Year | C1: College/Institute | D1: Title | E1: Author(s) | F1: Pub Type | G1: Journal/Book | H1: Category | I1: Keywords | J1: URL | K1: Citations | L1: Remarks
A2: 1 | B2: 2020 | C2: CAS | D2: Morpho-Anatomical Characterization of Rhododendron subsessile Rendle, an Endangered Species of the Cordillera Central Range, Philippines | E2: Jones T. Napaldet, Starleene S. Cervantes Mabel Grace V. Bitayan | F2: Journal | J2: https://link.springer.com/article/10.1007/s11676-019-01087-5
A3: 2 | B3: 2020 | C3: CF | D3: Ecological Services of Agroforestry Systems in Selected Upland Farming Communities in the Philippines | E3: Romnick S. Baliton*, Leila D. Landicho, Rowena Esperanza D. Cabahug, Roselyn F. Paelmo, Kenneth A. Laruan, Ramil S. Rodriguez, Roberto G. Visco, Arnold Karl A. Castillo | F3: Journal | J3: https://www.researchgate.net/publication/339064707_Ecological_services_of_agroforestry_systems_in_selected_upland_farming_communities_in_the_Philippines
A4: 3 | B4: 2020 | C4: NPRCRTC | D4: Confirmed Record of Spongospora subterranea subsp. Subterranea in Potato cv. Igorota in Northern Philippines and the Susceptability of Tomato cv. Yellow Plum to Spongospora Root Infection | E4: Mark Angelo Balendres & Teresita Masangcay | F4: Journal | J4: https://www.tandfonline.com/doi/abs/10.1080/03235408.2020.1717252
A5: 4 | B5: 2020 | C5: CAS | D5: Awareness and Compliance on Waste Segregation: Implication to a Waste Management Program in a University | E5: Bretel B. Dolipas, Jennifer Lyn S. Ramos, Monica S. Alimondo,Phil S. Ocampo & Danni Loven A. Fulwani | F5: Journal | J5: https://www.athensjournals.gr/sciences/2020-7-2-1-Dolipas.pdf
A6: 5 | B6: 2020 | C6: ISRD | D6: Adoption and economic analysis of using biological control in Philippine highland farms: Case of Trichoderma koningii strain KA | E6: Cheryll C. Launio, Kacy O. Labon, Alladin A. Bañez, Ruth S. Batani | F6: Journal | J6: https://www.sciencedirect.com/science/article/abs/pii/S0261219420301101
A7: 6 | B7: 2020 | C7: CF | D7: Estimation of Basic Wood Density and its Uncertainty for Quercus Species in South Korea | E7: Jung Kee Pyo, Roscinto Ian Lumbres, Yeong Mo Son, Kyeong Hak Lee, Young Jin Lee | F7: Journal | J7: https://ovcre.uplb.edu.ph/journals-uplb/index.php/JESAM/article/view/331
A8: 7 | B8: 2020 | C8: CF | D8: Crown Fuel Characteristics and Allometric Equations of Pinus densiflora in Gyeongbuk Province, Korea | E8: Sung Yong Kim, Roscinto Ian Lumbres, Yeon Ok Seo, Mina Jang, Sun Joo Lee, Byungdoo Lee, Young Jin Lee | F8: Journal | J8: https://ovcre.uplb.edu.ph/journals-uplb/index.php/JESAM/article/view/332/308
A9: 8 | B9: 2020 | C9: CA | D9: Identification of quantitative trait loci underlying resistance and tolerance to the rice root-knot nematode, Meloidogyne graminicola, in Asian rice (Oryza sativa) | E9: Judith Galeng-Lawilao, B. P. Mallikarjuna Swamy, Tapas Kumer Hore, Arvind Kumar & Dirk De Waele | F9: Journal | J9: https://link.springer.com/article/10.1007/s11032-020-01137-5
A10: 9 | B10: 2021 | C10: CF | D10: Nonlinear Height-DBH Model Analysis For Three Tropical Tree Species In Mt. Makiling, Philippines | E10: Nova D Doyog, Roscinto Ian C Lumbres, Feliciano G Calora Jr, Nelson M Pampolina, Michelle D Gamboa, Dante S Chichioco, Young Jin Lee | F10: Journal | J10: https://www.tandfonline.com/doi/abs/10.1080/10549811.2020.1775653?journalCode=wjsf20
A11: 10 | B11: 2020 | C11: CAS | D11: Absorption of Lead and Mercury in Dominant Aquatic Macrophytes of Balili River and Its Implication to Phytoremediation of Water Bodies | E11: Jones T. Napaldet and Inocencio E. Buot Jr. | F11: Journal | J11: https://www.ncbi.nlm.nih.gov/pmc/articles/PMC7470480/
A12: 11 | B12: 2020 | C12: CAS | D12: Distribution and morpho-anatomical characterization of ‘Beket’ (Coriaria japonica subsp. intermedia (Matsum) T. C. Huanh) in Cordillera Central Range, Northern Philippines | E12: Maricel Guron and Jones T. Napaldet | F12: Journal | J12: https://link.springer.com/article/10.1007/s11629-020-6110-7
A13: 12 | B13: 2020 | C13: NPRCRTC | D13: Adoption of Root crop- and Fruit–Based Processing Technologies | E13: Esther T. Botangen, Hilda L. Quindara and Joyce K. Mama-o | F13: Journal | J13: http://portal.bsu.edu.ph:8083/index.php/BRJ/article/view/260
... A43: 42 | B43: 2020 | C43: CA | D43: Growth, Morphological and Yield Characteristics of Five Potato (Solanum Tuberosum L) varieties Treated with Organic-Based Fertilizers | E43: Clement Michael, Belinda A. Tad-awan, Timothy Oluwafemi Ajiboye, Ighere Dickson | F43: Journal | J43: https://www.sumerianz.com/pdf-files/sjav3(4)46-53.pdf
A44: 43 | B44: 2020 | C44: ISRD | D44: Initiatives of Faculty Members in the Integration of IKS in the Tertiary Level Curriculum of Benguet State University | E44: Gigy G. Banes and Krisine Baniqued-Dela Cruz | F44: Policy Brief
A45: 44 | B45: 2020 | C45: ISRD | D45: Reinforcement of Political Engagement Among BSU Learners | E45: Ma. Theresa B. Dolipas | F45: Policy Brief
A46: 45 | B46: 2020 | C46: CA (Grad. School) | D46: Community-driven Metadata Standards for Agricultural Microbione Research | E46: J. P. Dundore-Arias, E. A. Eloe-Fadrosh, L. M. Schriml, G. A. Beattie, F. P. Brennan, P. E. Busby, R. B. Calderon, S. C. Castle, J. B. Emerson, S. E. Everhart, K. Eversole, K. E. Frost, J. R. Herr, A. I. Huerta, A. S. Iyer-Pascuzzi, A. K. Kalil, J. E. Leach, J. Leonard, J. E. Maul, B. Prithiviraj, M. Potrykus, N. R. Redekar, J. A. Rojas, K. A. T. Silverstein, D. J. Tomso, S. G. Tringe, B. A. Vinatzer, and L. L. Kinkel | F46: Journal | J46: https://doi.org/10.1094/PBIOMES-09-19-0051-P
A47: 46 | B47: 2020 | C47: ULIS | D47: Library usage by faculty members of Benguet State University | E47: Noel W. Cabfilan and Marjorie C. Ricardo | F47: Journal | J47: https://www.researchgate.net/profile/Noel-Cabfilan/publication/350153320_LIBRARY_USAGE_BY_FACULTY_MEMBERS_OF_BENGUET_STATE_UNIVERSITY/links/6053714192851cd8ce4f6d4c/LIBRARY-USAGE-BY-FACULTY-MEMBERS-OF-BENGUET-STATE-UNIVERSITY.pdf
A48: 47
A49: 48 | C49: Prepared by: | D49: NOEL A. LENGUAJE | E49: Noted by: CHERYLL C. LAUNIO
A50: 49 | D50: REPO Staff | E50: REPO Director
A51: 50
A52: 51
A53: 52
A54: 53
A55: 54
A56: 55
A57: 56
A58: 57
A59: 58 | J59: 0.375
A60: 59 | J60: 0.625
A61: 60
A62: 61
A63: 62
A64: 63
A65: 64
A66: 65
A67: 66
A68: 67
A69: 68
A70: 69
A71: 70

Sheet Data_2018_2019
A1: No. | B1: Year | C1: College/Institute | D1: Title | E1: Author(s) | F1: Pub Type | G1: Journal/Book | H1: Category | I1: Keywords | J1: URL | K1: Citations | L1: Remarks
A2: 1 | B2: 2018 | C2: CF | D2: Fitting and evaluation of height-diameter models for Alnus japonica in La Trinidad, Benguet, Philippines | E2: Roscinto Ian C. Lumbres, Nova D. Doyog, Kamae P. Anacioco, Judy Ann L. Gorio, Mary Relia S. Padsico, Young Jin Lee | F2: Journal | I2: Height- DBH model, Alnus japonica, Rank analysis, La Trinidad, Benguet, Philippines | J2: https://doi.org/10.1007/s11629-018-4866-9
A3: 2 | B3: 2018 | C3: CA | D3: Effects of Long-Term Subcultured Arbuscular Mycorrhizal Fungi on Red Pepper Plant Growth and Soil Glomalin Content | E3: Gopal Selvakumar, Pyoung Ho Yi, Seong Eun Lee, Charlotte C. Shagol, Seung Gab Han, Tongmin Sa & Bong Nam Chung | F3: Journal | I3: Arbuscular mycorrhizal fungi; Claroideoglomus; Gigaspora; glomalin; pepper | J3: https://doi.org/10.1080/12298093.2018.1461315
A4: 3 | B4: 2018 | C4: CNAS | D4: Students' Understanding of Physics Concepts, Attitude, Engagement, and Perceptions in a Flipped Classroom Environment | E4: Ederson Bawang and Maricar Prudente | F4: Journal | I4: Attitude; Flipped Classroom; Student Engagement; Student Understanding | J4: https://doi.org/10.1166/asl.2018.12463
A5: 4 | B5: 2018 | C5: CA | D5: First Report of Strawberry Necrotic Shock Virus in Strawberry in Benguet, Philippines | E5: Aurora F. Pinon and R.R.Martin | F5: Journal | I5: DNA sequencing, ELISA, geographical distribution, new geographic records, pathogens, plant diseases, plant pathogens, plant viruses, polymerase chain reaction, strawberries | J5: https://doi.org/10.1094/PDIS-03-18-0491-PDN
A6: 5 | B6: 2018 | C6: CF | D6: Mapping of the spatial distribution of carbon storage of the Pinus kesiya Royle ex Gordon (Benguet pine) forest in Sagada, Mt. Province, Philippines | E6: Nova D. Doyog, Roscinto Ian C. Lumbres and Young Jin Lee | F6: Journal | I6: Pinus kesiya, k-NN, AGB, AGC, Sagada, Philippines | J6: https://doi.org/10.1080/10549811.2018.1450155
A7: 6 | B7: 2018 | C7: CNS | D7: Fishes and Shell Diversity in Major Rivers of Benguet, Philippines | E7: Erlinda Bestre, Jones T. Napaldet, Arsenia M. Lumiquio | F7: Journal | I7: Benguet, diversity, freshwater fishes, shells | J7: https://www.researchgate.net/profile/Jones-Napaldet/publication/332980134_FISHES_AND_SHELL_DIVERSITY_IN_MAJOR_RIVERS_OF_BENGUET_PHILIPPINES/links/5cd54687299bf14d95877bbb/FISHES-AND-SHELL-DIVERSITY-IN-MAJOR-RIVERS-OF-BENGUET-PHILIPPINES.pdf
A8: 7 | B8: 2018 | C8: CN | D8: Reflecting on the Book of Alvesson and Skoldberg’ Reflexive Methodology: New Insights and its Importance in Qualitative Studies | E8: Jude L. Tayaben | F8: Journal | I8: Reflexive Research, Qualitative Method, Reflexivity, Research Procedures | J8: https://core.ac.uk/download/pdf/215364683.pdf
A9: 8 | B9: 2018 | C9: CAH | D9: Articulating the University's Vision and Mission and CAS Goals among Stakeholders | E9: Samuel S. Poliden, and Lourdes A. Bela-o | F9: Journal | I9: Awareness, Congruency, Comprehensibility, Attainability, University Vision and Mission | J9: https://d1wqtxts1xzle7.cloudfront.net/60193391/Articulating_VM...._published_article20190802-48056-mtagnt-libre.pdf?1564810479=&response-content-disposition=inline%3B+filename%3DARTICULATING_THE_UNIVERSITYS_VISION_AND.pdf&Expires=1710994861&Signature=AklegZ0O923XJcRBsNDag~Qc6iSqmDw-o7IHrjUGy4W~AjPyDIBPh-~biTOqUyS6sBWCcQuJzKy-u6cl-83CTEz2a-Cnh2dP7SEUsxNoqU6QTf8Nv0EhSehFqOvqY~~tmKScnQkZz5jn6jIv1RNTIGelR4AL0zxtOfWLvr8fUNfYihBEwuowf0zy0l3rNhVhu0LgG-bHDa360CJmEDCjQi-OCXDcJHvHGKEr4BD0b74W5VujOUKofteKeQP5y9VItXHXZNdLwCWx2vK5pjezOUrGNhDOlBCNgWn-n0OM2dhKiW7f6dXB9rWOq5fKr-kIIHXj2ViE2BXPNKFSoP73nA__&Key-Pair-Id=APKAJLOHF5GGSLRBV4ZA
A10: 9 | B10: 2018 | C10: CNAS | D10: Waste Handling Practices and Values of University Student | E10: Bretel B. Dolipas, Jennifer Lyn S. Ramos, Monica S. Alimondo, Carmelo Madinno | F10: Journal | I10: Disposal, Home origin, Segregation, Student values, Waste handling | J10: https://athensjournals.gr/health/2018-5-3-3-Dolipas.pdf
A11: 10 | B11: 2018 | C11: CTE | D11: Contextualizing Teaching Practices in a Diversified Classroom: An Assessment | E11: Percyveranda Lubrica, Janet Lynn Montemayor, Evelyn Angiwan and Arnulfo Capili | F11: Journal | I11: cognitive preference modality, pedagogical approach, classroom diversity, teaching practices, differentiated instruction | J11: https://www.eurrec.org/ijote-article-6837
A12: 11 | B12: 2018 | C12: CNAS | D12: Motivation of Secondary Mathematics Pre-Service Teachers in Choosing Mathematics as Their Career | E12: Carmelo W. Madinno | F12: Journal | I12: Career Motivation; Mathematics Education; Pre-Service Teachers | J12: https://doi.org/10.1166/asl.2018.12448
A13: 12 | B13: 2018 | C13: CA | D13: Spore Associated Bacteria Regulates Maize Root K+/Na+ Ion Homeostasis to Promote Salinity Tolerance during Arbuscular Mycorrhizal Symbiosis | E13: Gopal Selvakumar, Charlotte C. Shagol, Kiyoon Kim, Seunggab Han and Tongmin Sa | F13: Journal | I13: Arbuscular mycorrhizal fungi, Spore associated bacteria, Plant-microbe interaction, gfp-tagging, Endophytic localization, Salt stress | J13: https://doi.org/10.1186/s12870-018-1317-2
... A39: 38 | B39: 2018 | C39: CF | D39: Flight for Conservation: The Birds of Benguet State University Land Reservations, La Trinidad, Benguet | E39: Gerry M. Alfonso | F39: Journal | I39: Birds, eco class, endemic species, indigenous species, exotic bird species, bird population trend | J39: http://portal.bsu.edu.ph:8083/index.php/BRJ/article/view/131
A40: 39
A41: 40 | B41: 2019 | C41: CF | D41: Stem volume models for Cryptomeria japonica of Jeju Island, Korea | E41: Nova D. Doyog, Roscinto Ian C. Lumbres, Young Jin Lee, Sung Cheol Jung, Yeon Ok Seo | F41: Journal | I41: Stem volume, model selection, model ranking, Jeju Island, Cryptomeria japonica | J41: https://doi.org/10.1080/10549811.2019.1570273
A42: 41 | B42: 2019 | C42: CN | D42: Review of Mixed Methods Research in Nursing Methodological Issues and Future Directions | E42: Jude L. Tayaben, Younas, Ahtisham; Pedersen, Maria | F42: Journal | I42: data integration, mixed methods, prevalence review, research methods | J42: https://doi.org/10.1097/nnr.0000000000000372
A43: 42 | B43: 2019 | C43: CNS | D43: Diversity of aquatic macrophytes in Balili River, La Trinidad,Benguet, Philippinesas potential phytoremediators | E43: Jones T. Napaldet and Inocencio E. Buot, Jr. | F43: Journal | I43: Balili River, diversity indices, macrophytes, phytoremediation | J43: https://doi.org/10.13057/biodiv/d200416
A44: 43 | B44: 2019 | C44: CNS | D44: Effect of phytoremediation on the morpho-anatomical characters of some aquatic macrophytes | E44: Jones T. Napaldet and Inocencio E. Buot, Jr., Macrina T. Zafaralla, Ireneo L. Lit, Jr., Rachel C. Sotto | F44: Journal | I44: Amaranthus spinosus, Eichhornia crassipes, Eleusine indica, morpho-anatomical, Pennisetum purpureum, phytoremediation | J44: https://doi.org/10.13057/biodiv/d200519
A45: 44 | B45: 2019 | C45: CNS | D45: Treatment of Balili River in Benguet, Philippines with constructed wetland planted with dominant local macrophytes | E45: Jones T. Napaldet and Inocencio E. Buot, Jr. | F45: Journal | I45: Phytoremediation, constructed wetland, Balili River, aquatic macrophytes, hydraulic retention time | J45: https://doi.org/10.1080/15226514.2019.1633268
A46: 45 | B46: 2019 | C46: CTE | D46: Information Literacy (IL) of College Freshmen: Implications for an IL Program in Academic Libraries | E46: Grace D. Quijano | F46: Journal | I46: Academic libraries, College freshmen, Information literacy | J46: https://digitalcommons.unl.edu/libphilprac/2502/
A47: 46 | B47: 2019 | C47: ICT | D47: E-learning roadmap for open distance learning in Cordillera Administrative Region | E47: Paul G. Garcia, Jr., D. H. Galeon, .J dela Cruz | F47: Proceedings | I47: no keywords | J47: https://iopscience.iop.org/article/10.1088/1757-899X/482/1/012012
A48: 47 | B48: 2019 | C48: CA | D48: Yield improvement with compost amendment and Trichoderma microbial inoculant (TMI) in rice paddies inundated by copper-rich mine tailings | E48: Cirilo A. Lagman, Jr., Virginia C. Cuevas, Xavier Anupo, Joey I. Orajay, and Frances G.E. Malamnao | F48: Journal | I48: mine tailings, Cu, rice, compost, Trichoderma, remediation | J48: https://scienggj.org/2019/PSL%202019-vol12-no01-p31-38-Cuevas%20et%20al.pdf
A49: 48 | B49: 2019 | C49: CA | D49: Comparison of the penetration, development and reproduction of Meloidogyne graminicola, and analysis of lignin and total phenolic content in partially resistant and resistant recombinant inbred lines of Oryza sativa | E49: Judith Galeng-Lawilao, Arvind Kumar, Ma. Teodora Nadong Cabasan, Dirk De Waele | F49: Journal | I49: Plant traits, Rice breeding, Root galls, Susceptibility | J49: https://doi.org/10.1007/s40858-018-0267-4
A50: 49 | B50: 2019 | C50: CNS | D50: Mastery Learning of Chemistry Competencies through the Spiral Progression Approach in Curriculum | E50: Luisita L. Ely | F50: Journal | I50: Chemistry Achievement Test (CAT), Learning Competencies, Mastery Learning, Spiral Progression Approach & Level of Mastery of Competencies | J50: https://d1wqtxts1xzle7.cloudfront.net/61150869/2.IJESROCT2019220191106-91385-1uucheb-libre.pdf?1573112958=&response-content-disposition=inline%3B+filename%3DMASTERY_LEARNING_OF_CHEMISTRY_COMPETENCI.pdf&Expires=1711014388&Signature=b1DGXskweyBmU7B83JOeJGzO2EZZgWMHnhqvUXMr9jx0cp~xaJ1JzrreYzvw5zIK22CamYUgdKLFIkK0F6DRxW75sCQdVMtkEub38IAvZ1XrtZycUYF~VfM9FdRH7pb6xLwHdS0EOhfbFWlPq6CTKVeXxtZVx43QwwqqVl5TWHmbrfGD7PUdgxL7FJ-AmYfGNesyKLRkXL8ueR-VeMYBAeLBPJVzGMPNKyz4JsUWnLMC01XC4j8CcNa0zKE5q~Mhle78RLidmOOzglii6MhdqvEbS~Xlhk3wdGyBW87I0XbMvG8biE4NwGAdFACWdSYb6e-2ph5-Zi~QceMoLGGehg__&Key-Pair-Id=APKAJLOHF5GGSLRBV4ZA
A51: 50 | B51: 2019 | C51: CE | D51: Design, Construction and Performance Evaluation of a Coco Peat Block Making Machine | E51: Zion Jemillinium S. Tam-awen, Rackielyn B. Piscador, Mirafel T. Afuyog | F51: Journal | I51: Coco Peat, Compression Ratio, Moisture Content, Blocking Capacity, Bulk Density | J51: https://pdfs.semanticscholar.org/3718/8e3a14e1a6c1d9c08d265e00710f0f79c143.pdf
A52: 51 | B52: 2019 | C52: CF | D52: Effect of Pollarding on the Survival Rate, Quantity and Sizeof Developed Branches of One-Year Old 'Beltik' and 'Dael' Seedlings | E52: John G. Tacloy | F52: Journal | I52: Not available | J52: http://dx.doi.org/10.33680/plsa.2019.020
... A84: 83 | B84: 2019 | C84: CHET/ISRD | D84: Traditional Food Crops and Their Role in the Nutrition Well-Being of a Semi-Subsistent Community in Kibungan, Benguet, Philippines | E84: Sherilyn B. Balauro and Matyline Camfili-Talastas | F84: Journal | I84: Nutrition, traditional food crops, post-harvest practices, 24-hour food recall, semi-subsistent community | J84: http://portal.bsu.edu.ph:8083/index.php/BRJ/article/view/246
A85: 84
A86: 85 | C86: Prepared by: | D86: NOEL A. LENGUAJE | E86: Noted by: CHERYLL C. LAUNIO
A87: 86 | D87: REPO Staff | E87: REPO Director
A88: 87
A89: 88
A90: 89
A91: 90
A92: 91
A93: 92
A94: 93
A95: 94
A96: 95
A97: 96
A98: 97
A99: 98
... A108: 107

Sheet Data_2017_below
A1: No. | B1: Year | C1: College/Institute | D1: Title | E1: Author(s) | F1: Pub Type | G1: Journal/Book | H1: Category | I1: Keywords | J1: URL | K1: Citations | L1: Remarks
A2: 1 | B2: 2017 | C2: CNS | D2: Floral Diversity Assessment of Balili River as Potential Phytoremediators | E2: Jones T. Napaldet, Inocencio E. Buot Jr | F2: Journal | I2: Alternanthera sessilis, Amaranthus spinosus, Cyperus distans, diversity indices, Eleusine indica, Pennisetum purpureum, phytoremediation | J2: https://www.researchgate.net/profile/Jones-Napaldet/publication/332980031_FLORAL_DIVERSITY_ASSESSMENT_OF_BALILI_RIVER_AS_POTENTIAL_PHYTOREMEDIATORS/links/5cd5454d299bf14d95877b44/FLORAL-DIVERSITY-ASSESSMENT-OF-BALILI-RIVER-AS-POTENTIAL-PHYTOREMEDIATORS.pdf
A3: 2 | B3: 2017 | C3: CNS | D3: Morpho-anatomical Characterization of Benguet Lily (Lilium philippinense Baker) | E3: Jones T. Napaldet, Inocencio E. Buot Jr | F3: Journal | I3: Lilium philippinense Baker, morphological and anatomical features | J3: https://www.researchgate.net/profile/Jones-Napaldet/publication/332963271_Morpho-Anatomical_Characterization_of_Benguet_Lily_Lilium_philippinense_Baker/links/5cd3f851458515712e9be092/Morpho-Anatomical-Characterization-of-Benguet-Lily-Lilium-philippinense-Baker.pdf
A4: 3 | B4: 2017 | C4: CF | D4: Evaluation of stem taper models fitted for Japanese cedar (Cryptomeria japonica) in the subtropical forests of Jeju Island, Korea | E4: Roscinto Ian C. Lumbres,Sung-Hyun Joo , Sung Cheol Jung | F4: Journal | I4: Diameter outside bark, Jeju province, kozak model, model evaluation, stem volume estimation | J4: https://doi.org/10.1080/21580103.2017.1393018
A5: 4 | B5: 2017 | C5: CA | D5: Chilling Differentially Affects Strawberries Grown under High-Temperature Conditions | E5: Nadine A. Ladesma, Curil S. Bagay, Justin C. Delgado, Danilo P. Padua | F5: Journal | I5: Chilling treatment, Fragaria x ananassa Duch., high temperature stress, strawberry, temperate fruits in the tropics | J5: https://d1wqtxts1xzle7.cloudfront.net/54149942/Ledesma_PAS.pdf?1502845904=&response-content-disposition=inline%3B+filename%3DChilling_differentially_affects_strawber.pdf&Expires=1711502954&Signature=BUvuBo7cpkGHK3~EwP042YzhvEsgmMj72Xx06yU6GvwOum5QYAH3decTVmLocoWurRYuxRMV6G04TJmu63UmVa-rqJJOUZgw1GbTIwe3CEUKcUwBG86aFcQUJb4VFx63LxuSyhFoyfv0O44f1y80h7KzvIw4Hdkxj30qE6lZVOMkWJxrlWuKlFb91CQPCkeZynS1DjHvEkxFJSbLaYkSuEYb-vYvENt5v3i7SyOaewbgxsFfVVi95Wwc7HVtBkh-rzCZW40dJq-MtkGrFCm9jnLYWOvqyNJ20mfQhWVKr~NSTFk52BNSN75R8ZplZH0IsG9lz9QELhEULbhdpSi6pg__&Key-Pair-Id=APKAJLOHF5GGSLRBV4ZA
A6: 5 | B6: 2017 | C6: CA | D6: Identification and characterization of endophytic fungi associated with the leaves of Moringa oleifera Lam. | E6: E.S. Carbungco, N.B. Pedroche, V.A. Panes, T.E. De la Cruz | F6: Journal | I6: explants, fungal endophytes, metabolites, morphospecies | J6: https://doi.org/10.17660/ActaHortic.2017.1158.42
A7: 6 | B7: 2017 | C7: CNS | D7: Detection of Organophosphate Residues in Selected Crops in Benguet and Mt. Province, Philippines | E7: Romeo A. Gomez, Jr., Gaudelia A. Reyes, David Y. Fomeg-as, Wileen Chiara T. Lasangen, Carljhonson Anacin | F7: Journal | I7: organophosphate, pesticide residue, pesticide residue accumulation, maximum residue limit (MRL) | J7: https://doi.org/10.47125/jesam/2017_2/04
A8: 7 | B8: 2017 | C8: CNS | D8: Morphological Characterization and Bacteriostatic Activity of Entomopathogenic Fungi Isolated from Short-horned Grasshopper (Oxya hyla intrica) | E8: Ronel C. Sogelio Jr., Jessa May H. Natura, James Kennard S. Jacob and Jennifer C. Paltiyan | F8: Journal | I8: Fungi, Grasshopper, Isolation, Morphological | J8: http://www.aatsea.org/images/conference_publications/pdf/v13_n7_3_2017_December/42_IJAT_13(7.3)_2017_Sogelio,%20Jr.%20RC_Microbial%20Biotechnology%20and%20Plant%20Protection.pdf
A9: 8 | B9: 2017 | C9: CNS | D9: Phytochemical Analysis, Larvicidal Activity and Cytotoxic Properties of Malvarosa (pelargonium graveolens) Leaf Extract | E9: Jennifer C. Paltiyan, Justin V. Dumale and Cynthia C. Divina | F9: Journal | I9: P. graveolens, phytochemical, larvicidal, cytotoxic properties, cell line (A549), proliferation | J9: https://www.researchgate.net/profile/Jennifer-Paltiyan/publication/326848290_Phytochemical_Analysis_Larvicidal_Activity_and_Cytotoxic_Properties_of_Malvarosa_Pelargonium_graveolens_Leaf_Extract/links/5e81f701458515efa0ba092c/Phytochemical-Analysis-Larvicidal-Activity-and-Cytotoxic-Properties-of-Malvarosa-Pelargonium-graveolens-Leaf-Extract.pdff
A10: 9 | B10: 2017 | C10: CF | D10: Tree Height Estimation of Pinus densiflora and Pinus koraiensis in Korea with the Use of UAV-Acquired Imagery | E10: Lynn Talkasen, Myeong Jun Kim, Dong Hyeon Kim, Dong Geun Kim, Kawn Hee Lee | F10: Journal | I10: unmanned aerial vehicle (UAV), digital surface model (DSM), height estimation, Pinus densiflora, Pinus koraiensis | J10: http://pdf.medrang.co.kr/Jfs/2017/033/Jfs033-03-03.pdf
A11: 10 | B11: 2017 | C11: CTE | D11: Five-Year Licensure Examination Performance of Library and Information Science Graduates | E11: Elizabeth A. Lascano, Apler J. Bansiong | F11: Journal | I11: Curricular programs, Librarians’ licensure examination (LLE), Passing rates, Bachelor of library and information science (BLIS), Center-Reviewees Self-Reviewees, First timers, Repeaters | J11: https://www.researchgate.net/profile/Elizabeth-Lascano/publication/354469581_Five-Year_Licensure_Examination_Performance_of_Library_and_Information_Science_Graduates/links/618dc3a0d7d1af224bdcd134/Five-Year-Licensure-Examination-Performance-of-Library-and-Information-Science-Graduates.pdf
A12: 11 | B12: 2017 | C12: CHET | D12: Ecological Solid Waste Management Practices of Households in the City Of Baguio: Basis for an Advocacy Program towards Climate Change Mitigation | E12: Rochelle B. Belino and Pelin B. Belino | F12: Journal | I12: ecological solid waste management | J12: not acccessible online as of March 2024
A13: 12 | B13: 2017 | C13: CE | D13: Design and Fabrication of a Passive Solar Dryer for Meat Preservation in the Cordillera Region of Northern Philippines | E13: Edgar M. Molintas | F13: Journal | I13: “etag”, highland, meat drying, Northern Philippines, passive solar dryer | J13: https://doi.org/10.22137/ijst.2017.v2n1.01
... A23: 22 | B23: 2017 | C23: CA | D23: Growth Performance of Finisher Broilers Fed with Ration Containing Potato (Solanum tuberosum) Meal as Partial Substitute to Corn | E23: Marlene B. Atinyao and Genevieve R. Tabon | F23: Journal | I23: Potato meal, broiler, finishing ration, growth performance | J23: http://journals.bsu.edu.ph/index.php/BRJ/article/view/21
A24: 23
A25: 24 | B25: 2016 | C25: CN | D25: Nurse informaticians report low satisfaction and multi-level concerns with electronic health records: results from an international survey | E25: Jude L Tayaben, Maxim Topaz, Charlene Ronquillo, Laura-Maria Peltonen, Lisiane Pruinelli, Raymond Francis Sarmiento, Martha K Badger, Samira Ali, Adrienne Lewis, Mattias Georgsson, Eunjoo Jeon, Chiu-Hsiang Kuo, Tasneem Islam, Janine Sommer, Hyunggu Jung, Gabrielle Jacklin Eler, Dari Alhuwail, Ying-Li Lee | F25: Proceedings | I25: attitude to computers, electronic health record, health personnel attitude, human, job satisfaction, nurse, nursing informatics, questionnaire, Attitude of Health Personnel, Electronic Health Records, Humans, Nurses, Surveys and Questionnaires | J25: https://pubmed.ncbi.nlm.nih.gov/28269961/
A26: 25 | B26: 2016 | C26: CN | D26: Nursing informatics research priorities for the future: recommendations from an international survey | E26: Tabayen, Jude L; Peltonen, Laura-Maria; Jeon, Eunjoo; Kuo, Chiu-Hsiang; Islam, Tasneem; Sommer, Janine; Jung, Hyunggu; Eler, Gabrielle Jacklin; AlHuwail, Dari; Topaz, Maxim; Ronquillo, Charlene Esteban; Pruinelli, Lisiane; Sarmiento, Raymond Francis; Badger, Martha Kimpton; Ali, Samira; Lewis, Adrienne; Georgsson, Mattias | F26: Book Chapter | I26: nursing informatics, future trends, big data, standard terminologies, informatics competencies | J26: https://www.researchgate.net/profile/Charlene-Ronquillo/publication/304750118_Nursing_Informatics_Research_Priorities_for_the_Future_Recommendations_from_an_International_Survey/links/59e71e2c4585151e54659ea7/Nursing-Informatics-Research-Priorities-for-the-Future-Recommendations-from-an-International-Survey.pdf
A27: 26 | B27: 2016 | C27: CN | D27: Advancing nursing informatics in the next decade: recommendations from an international survey | E27: Tabayen, J. L., Topaz, M., Ronquillo, C. E., Peltonen, L.-M., Pruinelli, L., Sarmiento, R. F., Badger, M. K., Ali, S., Lewis, A., Georgsson, M., Jeon, E., Kuo, C.-H., Islam, T., Sommer, J., Jung, H., Eler, G. J. and AlHuwail | F27: Book Chapter | I27: Nursing informatics, future trends, big data science, standard terminologies, informatics competencies | J27: https://www.researchgate.net/profile/Gabrielle-Eler/publication/320975563_Advancing_Nursing_Informatics_in_the_Next_Decade_Recommendations_from_an_International_Survey/links/5aedcfa3458515f59982fe80/Advancing-Nursing-Informatics-in-the-Next-Decade-Recommendations-from-an-International-Survey.pdf
A28: 27 | B28: 2016 | C28: CN | D28: Current Trends in Nursing Informatics: Results of an International Survey | E28: Jude Tabayen, Laura Maria Peltonen, Dari AlHuwail, Samira Ali, Martha Kimpton Badger, Gabrielle Jacklin Eler, Mattias Georgsson, Tasneem Islam, Eunjoo Jeon, Hyunggu Jung, Chiu-Hsiang Kuo, Adrienne Lewis, Lisiane Pruinelli, Charlene Esteban Ronquillo, Raymond Francis Sarmiento, Janine Sommer, Maxim Topaz | F28: Journal | I28: nursing, informatics, research trends, research priorities, international survey | J28: https://europepmc.org/article/med/27332419
A29: 28 | B29: 2016 | C29: CF | D29: Comparison of Stem Taper Models for the Four Tropical Tree Species in Mount Makiling, Philippines | E29: Roscinto Ian C. Lumbres, Azyleah C. Abino, Nelson M. Pampolina, Feliciano G. Calora Jr., Young Jin Lee | F29: Journal | I29: Mount Makiling Forest Reserve, Stem Volume Estimation, Diameter Outside Bark, Kozak Model, Tropical Trees Species | J29: https://doi.org/10.1007/s11629-015-3546-2
A30: 29 | B30: 2016 | C30: CA/NPRCRTC | D30: The adoption of cv. Igorota in the Philippines and Vietnam | E30: Dao Huy Chien, Zenaida N Ganga, Donita K Simongo, Cynthia G Kiswa, Ines C Gonzales, Jocelyn Perez, Pham Xuan Tung, Nguyen Tuyet Hau, Katrin Artola, Jari PT Valkonen, Canhui Li, Peter VanderZaag | F30: Journal | I30: Potato, Andigena, Late blight resistance, PVY resistance, PLRV resistance, Tropical highlands, Rapid multiplication | J30: https://doi.org/10.1007/s12230-016-9503-y
A31: 30 | B31: 2016 | C31: CF | D31: Performance of Weibull Function as a Diameter Distribution Model for Pinus thunbergii Stands in the Eastern Coast of South Korea | E31: Roscinto Ian Canicosa Lumbres, Azyleah Cañizares Abino, Sung Yong Kim, Mi Na Jang, Ho Joong Youn, Ki Hyung Park, Young Jin Lee | F31: Journal | I31: Aboveground biomass, Weibull distribution, Parameter recovery technique, Site index, Pinus thunbergii, Diameter distribution | J31: https://doi.org/10.1007/s11629-014-3243-5
A32: 31 | B32: 2016 | C32: CA | D32: Spore Associated Bacteria of Arbuscular Mycorrhizal Fungi Improve Maize Tolerance to Salinity by Reducing Ethylene Stress Level | E32: Gopal Selvakumar, Kiyoon Kim, Charlotte C. Shagol, Manoharan Melvin Joe, Tongmin Sa | F32: Journal | I32: Spore Associated Bacteria, ACC deaminase, Salt Stress, Ethylene Emission, PGP Functional Traits | J32: https://doi.org/10.1007/s10725-016-0184-9
A33: 32 | B33: 2016 | C33: CAH | D33: Enhancing Classroom Interaction Creatively | E33: Samuel S. Poliden | F33: Journal | I33: classroom practices, communication opportunities, authentic materials | J33: https://www.indianjournals.com/ijor.aspx?target=ijor:ijarmss&volume=5&issue=6&article=056
A34: 33 | B34: 2016 | C34: CTE | D34: Translation Competence of Pre-Service Teachers | E34: Dolores E. Alawas | F34: Journal | I34: Lexical, Mother Tongue, Pre-Service Teachers, Translation Competence, Semantic, Syntactic | J34: https://www.ijser.org/researchpaper/Translation-Competence-of-Pre-Service-Teachers.pdf
A35: 34 | B35: 2016 | C35: NPRCRTC | D35: Sustainable Potato Production in the Philippine Cordillera Region | E35: Ines C. Gonzales, Cynthia G. Kiswa, Arlene B. Bautista | F35: Journal | I35: Igorota variety, potato stem cuttings, seed production, tissue culture | J35: https://d1wqtxts1xzle7.cloudfront.net/103634200/IJEAS0306034-libre.pdf?1687407348=&response-content-disposition=inline%3B+filename%3DSustainable_Potato_Production_in_the_Phi.pdf&Expires=1711962808&Signature=aSb~2ShEHktzpjWM7bw4YlLKo05egR52aXfRF1KB-WCQ~b4Enrfbf1qMJnIwldUVW4YprWtH8pmaQZ7SFjegd8VeIRZjJ4IcLPyEJGwD-WWobzmowqZ2aEA3zv-9b-ITFseysmbQo~6GONFXE1h7TXHMG1TVKuLkvuTGvkgSuNfUfSwT75LeoGQSkOh5JAJ5qViVKjPgtqFfdVdBFYCB0ucrP6AVAsxa~xYi~jyvpbS9CZgMjKHAgtgermSQAxxDhTETfWMJXV5rDTC1uW-tMrMf8QRFIJzkQd98Fk3uQty1CO8eS5aDl4-hhtepfK4iRFCsJHgAWZDtWgjbyn7hcg__&Key-Pair-Id=APKAJLOHF5GGSLRBV4ZA
A36: 35 | B36: 2016 | C36: NPRCRTC | D36: Chickpea (garbanzos) Its’ Nutritional and Economical Value | E36: Ines C. Gonzales, Fernando R. Gonzales, Hilda L. Quindara, Pelin B. Belino, Esther T. Botangen | F36: Journal | I36: Buns, desi-type, kabuli-type, garbanzos, leche flan | J36: https://smartlib.umri.ac.id/assets/uploads/files/9e1be-a0704010106.pdf
A37: 36 | B37: 2016 | C37: NPRCRTC | D37: Evaluation of Potential Taro Cultivars Under La Trinidad Conditions | E37: Donita K. Simongo, Ines C. Gonzales | F37: Journal | I37: no access
A38: 37 | B38: 2016 | C38: NPRCRTC | D38: Evaluation on the Productivity of Cassava Intercropped with Bush Bean Under La Trinidad | E38: Lito M. Pacuz, Ines C. Gonzales, Donita K. Simongo | F38: Journal | I38: Bush beans, cassava, intercropped
A39: 38 | B39: 2016 | C39: CA | D39: Extracellular cell wall-degrading enzyma as mycopesticide derived from Beauveria bassiana against tomato black lead mold (Pseudocercospora fuligena) | E39: JI Yago, AD Agrimor, JLP Baligad, ET Irabagon, LM Villanueva, RG Maghirang | F39: Journal | I39: Beauveria bassiana, enzymes, degradation, Pseudocercospora, Entomogenous fungi, plant diseases
A40: 39 | B40: 2016 | D40: Survey of insects, mites and slugs associated with selected fruit crops grown in the Provinces of the Cordillera Administrative Region (CAR)[Philippines] | E40: LM Faroden, LM Colting, KJP Eladjoe, AT Manuel, MR Parao, JD Bacbac | F40: Journal | I40: Tetranychus urticae, Tetranychidae, Oecophylla, mangoes, Pentalonia, bananas, pests of plants, Arbutus, Pentalonia nigronervosa, Banana bunchy top virus, Harmony, Arthropoda
A41: 40 | B41: 2016 | D41: Design and Fabrication of a Hydraulic Diaphragm Pump | E41: Melba D. Denson, Marlon N. Galad, and John James F. Malamug | F41: Journal | I41: development, hydraulic diaphragm pump, motorless, energy from moving water, irrigation
A42: 41 | B42: 2016 | D42: Development of a Vertical Disc Push-Type Double-Row Carrot Seeder for Small-Scale Farmers | E42: Marvin T. Valentin | F42: Journal | I42: carrot seeder; fabrication; field capacity; field efficiency; evaluation
A43: 42 | B43: 2016 | D43: Analysis of Nutritional Status and Income of Landless Agricultural Workers and Their Households from Two Villages in Calauan, Laguna, Philippines | E43: Alessandro A. Manilay, Imelda Degay, Lilibeth O. Furoc and Rico C. Ancog | F43: Journal | I43: landless farm workers, caloric intake, poverty threshold
A44: 43 | B44: 2016 | D44: From Shaking to Shining: Reducing Students’ Language Anxiety through Outcome Thinking Protocol | E44: Myrna B.Sison-Kuiper | F44: Journal | I44: Language Anxiety, Outcome Thinking Protocol Approach, Lived Experiences, Case Study
A45: 44 | B45: 2016 | D45: Interactive physics apparatus: influence on interest of secondary school students in pursuing a career path in science, technology, engineering and mathematics (STEM) | E45: Joel V Lubrica, Jovalson T Abiasen, Bretel B Dolipas, Jennifer Lyn S Ramos | F45: Journal | I45: Secondary School Science, Physics, Science Instruction, Junior High School Students, Science Laboratories, Laboratory Equipment, STEM Education, Student Attitudes, Student Interests, Career Choice, Foreign Countries, Laboratory Schools, Likert Scales
A46: 45 | B46: 2016 | D46: A Technique of Teaching the Principle of Equivalence at Ground Level | E46: Joel V Lubrica | F46: Journal | I46: Teaching Methods, Scientific Methodology, Scientific Principles, Demonstrations (Educational), Motion, Scientific Concepts, Physics, Class Activities
A47: 46 | B47: 2016 | D47: Bimetal switches in an AND logic gate | E47: Joel V Lubrica and Quantum Yuri B Lubrica | F47: Journal | I47: no access
A48: 47 | B48: 2016 | D48: Stem volume Models and Validation for Cryptomeria japonica in Jeju Island, Korea | E48: YeonOk Seo, Sung Cheol Jung, Roscinto Ian Lumbres, Chul Hyun Jeon, Chan Soo Kim | F48: Journal | I48: no keywords
A49: 48 | B49: 2016 | D49: Valuing underutilized sweetpotato (Ipomoea batatas L.) comparing a yellow and dark purple fleshed cultivar: its nutritional content and economic potential | E49: Gonzales, I. C., Botangen, E. T., Mama-o, J. K. | F49: Journal | I49: camote, Cordillera, hopia, yoghurt
A50: 49 | B50: 2016 | D50: Verbal Learning Style as the Least Preferred Learning Style of Students in an Asian Country | E50: Samuel S. Poliden | F50: Journal | I50: Education, learning styles, dominant learning styles, language class, communication skills, descriptive design, Philippines
A51: 50 | B51: 2016 | D51: Growth Performance and Coccidia Occurrence in Philippine Native Chicken Given Diets Added with Organic Selenium, Probiotics and Prebiotics | E51: Monaliz M. Nagrampa, Josefina Linda B. Manugo, Clarita S. Puso | F51: Journal | I51: coccidia, native chicken, oocyst, prebiotic, probiotic
... A73: 72 | B73: 2016 | D73: Exploring the Sexual Scripts of Adolescents | E73: Ann Heather B. Kiwang | F73: Journal | I73: sexual scripts, cultural scripts, interpersonal scripts, intrapersonal scripts
A74: 73
A75: 74 | D75: Factors Affecting the Academic Performance of the Student Nurses of BSU | E75: Sunshine B. Alos, Lawrence C. Caranto, Juan Jose T. David | F75: Journal | I75: Academic performance, Home-related aspects, Personal condition, School-related aspects, Study habits, Teacher-related aspects
A76: 75 | D76: Evaluation and validation of stem volume models for Quercus glauca in the subtropical forest of Jeju Island, Korea | E76: Yeon Ok Seo, Roscinto Ian C Lumbres, Hyun Kyu Won, Sung Cheol Jung, Young Jin Lee | F76: Journal | I76: forest management, gotjawal forest, model evaluation, model validation, Mt. Halla, Sub-tropical forests
A77: 76 | D77: Awareness, Understanding, and Acceptance of Student Nurses of the Vision, Mission, Goals, and Objectives of Benguet State University | E77: Keren Joy T. Compelio, Lawrence C. Caranto, Juan Jose T. David | F77: Journal | I77: Vision, mission, Goals, and objectives (VMGO), Awareness, Understanding, and acceptance, Student nurses
A78: 77 | D78: DBH-height modeling and validation for Acacia mangium and Eucalyptus pellita in Korintiga Hutani Plantation, Kalimantan, Indonesia | E78: Roscinto Ian C Lumbres, Young Jin Lee, Chung Weon Yun, Chang Duck Koo, Se Bin Kim, Yeong Mo Son, Kyeong Hak Lee, Hyun Kyu Won, Sung Cheol Jung, Yeon Ok Seo | F78: Journal | I78: nonlinear growth models, tropical plantation, DBH-height models, evaluation statistics, model validation
A79: 78 | D79: Compliance with sharps injury prevention guideline among nurses in tertiary care hospitals in the Philippine | E79: Jude L. Tayaben | F79: Journal | I79: Needlestick injuries and prevention and control; Practice guidelines as topic; Compliance; Nurses
A80: 79 | D80: Competencies of Library and Information Science Graduates: Implications for Outcomes Based Teaching and Learning | E80: Grace D. Quijano | F80: Journal | I80: Outcomes; Competencies; Education
A81: 80 | D81: Experiential Learning In Library And Information Science (LIS) Education Through Out-Campus Practicum | E81: Grace D. Quijano | F81: Journal | I81: experiential learning; out-campus practicum; competencies
A82: 81 | D82: Design, Fabrication, and Performance Evaluation of a Poato (Solanum tuberosum L.) Grader for Village Level Operations | E82: Marvin VALENTIN, , Elmar VILLOTA, Vitalliana MALAMUG and Ireneo AGULTO | F82: Journal | I82: Premium price, manual grading, laborious, potato grader, village-level
A83: 82 | D83: Identification and characterization of endophytic fungi associated with the leaves of Moringa oleifera Lam. | E83: E.S. Carbungco, N.B. Pedroche, V.A. Panes, T.E. De la Cruz | F83: Journal | I83: explants, fungal endophytes, metabolites, morphospecies
A84: 83 | D84: Needs and opportunities assessment and documentation on farming practices on heirloom rice production in Benguet [Philippines] | E84: BA Tad-awan, RS Batani, JM Sim, BS Tad-awan, CP Laurean, EJD Sagalla, TD Masangcay, MP Odiaz | F84: Journal | I84: farming systems, Philippines, farmers, documentation, Oryza sativa
A85: 84 | D85: Value-Adding of Cordillera Pork-based Ethnic Food Delicacy (Etag) for Commercialization | E85: Sonwright B Maddul, Ruth S Batani, Sherilyn B Balauro, Cynthia D Garambas, Myrna B Walsiyen | F85: Journal | I85: no keywords
A86: 85 | D86: Students’ Perspectives of Bullying Behaviors Experienced in Nursing Education: A Descriptive Cross-Sectional Study | E86: Jude L Tayaben, Doris S Natividad, Rovencio E Apilado | F86: Journal | I86: no access
... A102: 101 | D102: S&T Based Farm on Enhanced Production of Spray-Type Chrysanthemum through Integrated Crop Management | E102: CP Laurean, AB Colte, ND Organo, TK Mangili and SB Maddul | F102: Journal | I102: no keywords
A103: 102 | F103: Journal
A104: 103 | D104: Arsenic-tolerant plant-growth-promoting bacteria isolated from arsenic-polluted soils in South Korea | E104: Charlotte C. Shagol, Ramasamy Krishnamoorthy, Kiyoon Kim,Subbiah Sundaram, Tongmin Sa | F104: Journal | I104: Arsenic-tolerant bacteria, Genetic diversity, Plant growth promotion, Phytoremediation
A105: 104 | D105: Comparative analysis of four stem taper models for Quercus glauca in Mount Halla, Jeju Island, South Korea | E105: Roscinto Ian Canicosa Lumbres, Young Jin Lee, Hyung Soon Choi, Sung Yong Kim, Mi Na Jang, Azyleah Cañizares Abino, Yeon Ok Seo, Chan Soo Kim, Jung Hwan Park | F105: Journal | I105: Mount Halla, Merchantable stem volume, Diameter outside bark, Kozak model, Model evaluation
A106: 105 | D106: Development and Evaluation of Modules in Technical Writing | E106: Ma. Theresa B. Nardo, Esther R. Hufana | F106: Journal | I106: module development, modular instruction, evaluation, technical writing
A107: 106 | D107: Aboveground biomass mapping of La Trinidad forests in Benguet, Philippines, using Landsat Thematic Mapper data and k-nearest neighbor method | E107: Roscinto Ian C Lumbres, Young Jin Lee | F107: Journal | I107: Pinus kesiya, k-nearest neighbor, Landsat Thematic Mapper, tropical forests, aboveground biomass
A108: 107 | D108: Percentile-based Weibull diameter distribution model for Pinus kesiya stands in Benguet province, Philippines | E108: Roscinto Ian C Lumbres, Young Jin Lee | F108: Journal | I108: growth and yield model, parameter recovery method, tropical forests, Weibull distribution
A109: 108 | D109: The Effects of Arbuscular Mycorrhizal Fungi (AMF) as Biofertilizer on the Growth, Yield and Nutrient Uptake of Tomato (Lycopersicon esculentum Mill.) | E109: Precelita L. Osillos, Asuncion L. Nagpala | F109: Journal | I109: AMF, colonized roots, biofertilizer, tomato, Acaulospora
A110: 109 | D110: Floral diversity assessment in Alno communal mixed forest in Benguet, Philippines | E110: Roscinto Ian C Lumbres, Jennifer A Palaganas, Sheryll C Micosa, Kenneth A Laruan, Elvira D Besic, Chung-Weon Yun, Young-Jin Lee | F110: Journal | I110: Biodiversity, Vegetational analysis, Diversity index, Pinus kesiya
A111: 110 | D111: Attitudes of student nurses enrolled in e-learning course towards academic dishonesty: a descriptive-exploratory study | E111: Jude L. Tayaben | F111: Journal | I111: Attitudes of student nurses, e- Learning course, academic dishonesty,bacademic- integrity,responsibility
A112: 111 | D112: Development of stem taper equations for Pinus kesiya in Benguet province, Philippines | E112: Roscinto Ian C Lumbres, Jung Kee Pyo, Young Jin Lee | F112: Journal | I112: tropical forests, merchantable stem volume, diameter outside bark, forest management, model evaluation
A113: 112 | E113: Laconsay, Eduardo P | F113: Journal | I113: wellness, fitness, physical and environmental dimensions, health related fitness, stress debriefing activities and nutrition
A114: 113 | D114: Allometric equations, stem density and biomass expansion factors for Cryptomeria japonica in Mount Halla, Jeju Island, Korea | E114: Sung Cheol Jung, Roscinto Ian C Lumbres, Hyun Kyu Won, Yeon Ok Seo | F114: Journal | I114: allometric equation;biomass;biomass expansion factor;Cryptomeria japonica;Mount Halla;stem density
A115: 114 | D115: Undertaking as a Concrete Enquiry: A Review of Penny Tinkler's Using Photographs in Social and Historical Research | E115: Jude L. Tayaben | F115: Journal | I115: Photographs, Social and Historical Research, Qualitative Inquiry
A116: 115 | D116: Assessment of the Ladderized Bachelor of Science in Entrepreneurial Technology Curriculum of Benguet State University | E116: Elvena P. Belino | F116: Journal | I116: Ladderized Bachelor of Science in Entrepreneur Technology (BSET), Benguet State University
A117: 116 | D117: Error Identification of Written Discourses of English Major Students: An Underpinning for a Program Study | E117: Kara S. Panolong | F117: Journal | I117: error identification, written discourses, English majors
A118: 117 | D118: “TRUE” Measure of Lithophytes Diversity Across Microclimate | E118: Norbert Q. Angalan, Gaudelia A. Reyes and Romeo A. Gomez, Jr. | F118: Journal | I118: diversity, microclimate, lithophytes
A119: 118 | D119: Potential of Bacillus Subtilis Against Powder Mildew of Garden Pea | E119: LM Villanueva, JZD Ibis, AS Dayao | F119: Journal | I119: no keywords
A120: 119 | D120: KFS-P34: Weibull Diameter Distribution Modelling for Benguet pine (Pinus kesiya) stands of the Northern Province in the Philippines | E120: Roscinto Ian C Lumbres, Hyun Kyu Won, Sung Cheol Jung, Yeon Ok Seo, Young Jin Lee | F120: Journal | I120: no access
A121: 120 | D121: Variety evaluation, on-farm trials and genotype x environment (G x E) analysis, on semi-temperate vegetable for organic production in four agro-ecological zones of the Cordillera highlands [Philippines] | E121: BA Tad-awan, DF Basquial | F121: Journal | I121: Lycopersicon esculentum, Brassica chinensis, Brassica oleracea capitata, Philippines, Daucus carota
A122: 121 | D122: Price volatility of selected high value vegetables in Cordillera Administrative Region, Philippines | E122: Samuel L. Duyan, Leopoldo N. Tagarino | F122: Journal | I122: Price volatility, price trend, highland vegetables
A123: 122 | D123: Screening of Sweetpotato Genotyoes for Water Stress Resistance | E123: Agnes C. Perey, Belinda A. Tad-awan | F123: Journal | I123: genotypes, drought resistance, greenhouse
A124: 123 | D124: Analysis of the Level of Inquiry in the Undergraduate Science Education Laboratory | E124: Apler J. Bansiong | F124: Journal | I124: Inquiry, Levels of Inquiry, Science education majors, K – 12 science education
A125: 124 | D125: Nutritional Status and School Performance of 4P’s Elementary School Children in La Trinidad, Benguet | E125: Johanne D. Martinez, Vallorie T. Medona, Gia Lenn L. Mendoza and Kryme D. Rosita | F125: Journal | I125: no keywords
... A137: 136 | D137: Development of Root Crops Wheat Flour Formulations for Quality Fresh Miki Noodles | E137: VB Salda and CB Esnara | F137: Journal | I137: no keywords
A138: 137
A139: 138 | D139: Higher order thinking skills and academic performance in physics of college students: A regression analysis | E139: Jennifer Lyn S Ramos, Bretel B Dolipas, Brenda B Villamor | F139: Journal | I139: Higher order thinking skills, academic performance, physics, college students, regression analysis
A140: 139 | D140: Cataloging and Classification Skills of Library and Information Science Practitioners in their Workplaces: A Case Analysis | E140: Russell B. Dolendo and David A. Cabonero | F140: Journal | I140: Cataloging skills, Catalogers, Subject analysis, Descriptive cataloging, Subject cataloging, Case analysis, Library practitioners
A141: 140 | D141: Influence of stand age class on biomass expansion factor and allometric equations for Pinus rigida plantations in South Korea | E141: Yeon Ok Seo, Young Jin Lee, Roscinto Ian C Lumbres, Jung Kee Pyo, Rae Hyun Kim, Yeong Mo Son, Kyeong Hak Lee | F141: Journal | I141: Age classes, allometric equations, biomass expansion factor, biomass partitioning, stem density
A142: 141 | D142: Model fitting and validation of six height–DBH equations for Pinus kesiya Royle ex Gordon in Benguet Province, Philippines | E142: Roscinto Ian C Lumbres, Young Jin Lee, Feliciano G Calora Jr, Marissa R Parao | F142: Journal | I142: Pinus kesiya , nonlinear growth functions, height–DBH relationship, Modified Logistic model, forest inventory
A143: 142 | D143: Development and validation of stem volume models for Pinus kesiya in Benguet province, Philippines | E143: Roscinto Ian C Lumbres, Young Jin Lee | F143: Journal | I143: forest management, model evaluation, Pinus kesiya , tropical forests, volume equations
A144: 143 | D144: Plant-parasitic nematodes associated with semi-temperate vegetables in the highlands of Benguet Province, Philippines | E144: Nordalyn B Pedroche, Luciana M Villaneuva, Dirk De Waele | F144: Journal | I144: frequency of occurrence, highlands, Philippines, plant-parasitic nematodes, population density, survey, vegetables
A145: 144 | D145: Online Student Information System Of Benguet State University (OSIS-BSU) | E145: Rochelle D. Pacio | F145: Journal | I145: Benguet State University, Online Student Information System (OSIS), Rapid Application Development (RAD), Database, Client and Server
A146: 145 | D146: Food Sufficiency in the Terraces: The Case of Globally-Important Agricultural Heritage Systems In Ifugao, Central Cordillera, Philippines | E146: Romeo Gomez Jr. | F146: Journal | I146: no access
A147: 146 | D147: Potential of Bacillus subtilis against powder mildew of garden pea | E147: LM Villanueva, JZD Ibis, AS Dayao | F147: Journal | I147: biological control, biological control agents, crop yield, egg yolk, fungal diseases, garlic, leaves, natural enemies, pathogens, peas, plant disease control, plant diseases, plant extracts, plant pathogenic fungi, plant pathogens, rapeseed oil, silicon, sodium bicarbonate, stems, sweet peppers, vegetables, mildews, powdery mildew
A148: 147 | D148: Assault and Violence Prevention and Management in In-Patient Psychiatric Units | E148: Jocelyn C. Perez | F148: Journal | I148: Violence prevention, crisis management, assaults, aggression, practice guidelines
A149: 148 | D149: Rhizobacteria: Restoration of Heavy Metal-Contaminated Soils | E149: Seifeddine Ben Tekaya, Sherlyn Tipayno, Kiyoon Kim, Parthiban Subramanian, Tongmin Sa | F149: Journal | I149: Heavy Metal, Metal Uptake, Metal Removal, Plant Growth Promotion, Metal Stress
A150: 149 | D150: Graphic Materials as Catalyst in Reading Comprehension | E150: Samuel S. Poliden | F150: Journal | I150: Graphic Materials, Reading Comprehension, Authentic Materials, Reading Materials, Reading Comprehension Skill, Philippines
... A159: 158 | D159: Relationship Between University Students’ Multiple Intelligences and Academic Performance | E159: M. A. B. Lubrica & J. V. Lubrica | F159: Journal | I159: Multiple Intelligences, Academic Performance, Statistics Students
A160: 159 | D160: Negotiating Climate Change: Vulnerabilities and Resilience of Four Benguet Communities | E160: Batani, Ruth S., J. Napaldet, M. Camfili, M. Gapasin, K. C. Ngina | F160: Journal
A161: 160 | D161: Development of a Graduate Educational Research Competency Test | E161: J. L. S. Montemayor | F161: Journal | I161: test development, research competency, graduate education, principal component analysis
A162: 161 | D162: Geographic Information System of Vegetable and Crop Production in Benguet | E162: J. B. Lacea | F162: Journal | I162: Decision-Support System, Factor Analyses, GPS, Information System, Spatial Data Analysis, Software Architecture, UM
A163: 162
A164: 163 | D164: Evaluation of height-diameter models for three tropical plantation species in the Philippines | E164: Roscinto Ian C Lumbres, Dalisay E Cabral, Marissa R Parao, Yeon Ok Seo, Young Jin Lee | F164: Journal | I164: no access
...
